{"timestamp":"2022-10-21T23:55:39Z","previous_timestamp":"2022-10-21T23:50:39Z","next_timestamp":"2022-10-22T00:00:39Z","data":[{"id":"a7dbe0bb4ed8e04b8d8d1e54d9492c62","sport_key":"mma_mixed_martial_arts","sport_title":"MMA","commence_time":"2022-10-22T14:15:00Z","home_team":"Lina Lansberg","away_team":"Karol Rosa","bookmakers":[{"key":"fanduel","title":"FanDuel","last_update":"2022-10-21T23:51:11Z","markets":[{"key":"h2h","last_update":"2022-10-21T23:51:11Z","outcomes":[{"name":"Karol Rosa","price":-400},{"name":"Lina Lansberg","price":300}]}]},{"key":"betonlineag","title":"BetOnline.ag","last_update":"2022-10-21T23:52:00Z","markets":[{"key":"h2h","last_update":"2022-10-21T23:51:59Z","outcomes":[{"name":"Karol Rosa","price":-345},{"name":"Lina Lansberg","price":285}]}]},{"key":"mybookieag","title":"MyBookie.ag","last_update":"2022-10-21T23:48:51Z","markets":[{"key":"h2h","last_update":"2022-10-21T23:48:51Z","outcomes":[{"name":"Karol Rosa","price":-370},{"name":"Lina Lansberg","price":267}]}]},{"key":"draftkings","title":"DraftKings","last_update":"2022-10-21T23:51:10Z","markets":[{"key":"h2h","last_update":"2022-10-21T23:51:10Z","outcomes":[{"name":"Karol Rosa","price":-330},{"name":"Lina Lansberg","price":275}]}]},{"key":"wynnbet","title":"WynnBET","last_update":"2022-10-21T23:53:38Z","markets":[{"key":"h2h","last_update":"2022-10-21T23:53:38Z","outcomes":[{"name":"Karol Rosa","price":-345},{"name":"Lina Lansberg","price":270}]}]},{"key":"williamhill_us","title":"William Hill (US)","last_update":"2022-10-21T23:52:52Z","markets":[{"key":"h2h","last_update":"2022-10-21T23:52:52Z","outcomes":[{"name":"Karol Rosa","price":-340},{"name":"Lina Lansberg","price":270}]}]},{"key":"betfair","title":"Betfair","last_update":"2022-10-21T23:52:00Z","markets":[{"key":"h2h","last_update":"2022-10-21T23:52:00Z","outcomes":[{"name":"Karol Rosa","price":-345},{"name":"Lina Lansberg","price":330}]},{"key":"h2h_lay","last_update":"2022-10-21T23:52:00Z","outcomes":[{"name":"Karol Rosa","price":-333},{"name":"Lina Lansberg","price":350}]}]},{"key":"barstool","title":"Barstool Sportsbook","last_update":"2022-10-21T23:54:23Z","markets":[{"key":"h2h","last_update":"2022-10-21T23:54:23Z","outcomes":[{"name":"Karol Rosa","price":-345},{"name":"Lina Lansberg","price":260}]}]},{"key":"sugarhouse","title":"SugarHouse","last_update":"2022-10-21T23:53:38Z","markets":[{"key":"h2h","last_update":"2022-10-21T23:53:38Z","outcomes":[{"name":"Karol Rosa","price":-345},{"name":"Lina Lansberg","price":260}]}]},{"key":"betrivers","title":"BetRivers","last_update":"2022-10-21T23:54:25Z","markets":[{"key":"h2h","last_update":"2022-10-21T23:54:25Z","outcomes":[{"name":"Karol Rosa","price":-345},{"name":"Lina Lansberg","price":260}]}]},{"key":"twinspires","title":"TwinSpires","last_update":"2022-10-21T23:54:23Z","markets":[{"key":"h2h","last_update":"2022-10-21T23:54:23Z","outcomes":[{"name":"Karol Rosa","price":-345},{"name":"Lina Lansberg","price":260}]}]},{"key":"lowvig","title":"LowVig.ag","last_update":"2022-10-21T23:53:47Z","markets":[{"key":"h2h","last_update":"2022-10-21T23:53:46Z","outcomes":[{"name":"Karol Rosa","price":-345},{"name":"Lina Lansberg","price":285}]}]},{"key":"betmgm","title":"BetMGM","last_update":"2022-10-21T23:54:22Z","markets":[{"key":"h2h","last_update":"2022-10-21T23:54:22Z","outcomes":[{"name":"Karol Rosa","price":-350},{"name":"Lina Lansberg","price":275}]}]},{"key":"superbook","title":"SuperBook","last_update":"2022-10-21T23:54:23Z","markets":[{"key":"h2h","last_update":"2022-10-21T23:54:23Z","outcomes":[{"name":"Karol Rosa","price":-350},{"name":"Lina Lansberg","price":290}]}]},{"key":"bovada","title":"Bovada","last_update":"2022-10-21T23:55:16Z","markets":[{"key":"h2h","last_update":"2022-10-21T23:55:16Z","outcomes":[{"name":"Karol Rosa","price":-350},{"name":"Lina Lansberg","price":260}]}]},{"key":"unibet_us","title":"Unibet","last_update":"2022-10-21T23:53:39Z","markets":[{"key":"h2h","last_update":"2022-10-21T23:53:39Z","outcomes":[{"name":"Karol Rosa","price":-345},{"name":"Lina Lansberg","price":260}]}]}]},{"id":"0d169754edaa08d93d008f6adcfb3ea5","sport_key":"mma_mixed_martial_arts","sport_title":"MMA","commence_time":"2022-10-22T14:45:00Z","home_team":"Muhammad Mokaev","away_team":"Malcolm Gordon","bookmakers":[{"key":"draftkings","title":"DraftKings","last_update":"2022-10-21T23:51:10Z","markets":[{"key":"h2h","last_update":"2022-10-21T23:51:10Z","outcomes":[{"name":"Malcolm Gordon","price":800},{"name":"Muhammad Mokaev","price":-1250}]}]},{"key":"williamhill_us","title":"William Hill (US)","last_update":"2022-10-21T23:52:52Z","markets":[{"key":"h2h","last_update":"2022-10-21T23:52:52Z","outcomes":[{"name":"Malcolm Gordon","price":750},{"name":"Muhammad Mokaev","price":-1200}]}]},{"key":"fanduel","title":"FanDuel","last_update":"2022-10-21T23:51:11Z","markets":[{"key":"h2h","last_update":"2022-10-21T23:51:11Z","outcomes":[{"name":"Malcolm Gordon","price":880},{"name":"Muhammad Mokaev","price":-1800}]}]},{"key":"betonlineag","title":"BetOnline.ag","last_update":"2022-10-21T23:52:00Z","markets":[{"key":"h2h","last_update":"2022-10-21T23:51:59Z","outcomes":[{"name":"Malcolm Gordon","price":850},{"name":"Muhammad Mokaev","price":-1429}]}]},{"key":"mybookieag","title":"MyBookie.ag","last_update":"2022-10-21T23:48:51Z","markets":[{"key":"h2h","last_update":"2022-10-21T23:48:51Z","outcomes":[{"name":"Malcolm Gordon","price":709},{"name":"Muhammad Mokaev","price":-1428}]}]},{"key":"wynnbet","title":"WynnBET","last_update":"2022-10-21T23:53:38Z","markets":[{"key":"h2h","last_update":"2022-10-21T23:53:38Z","outcomes":[{"name":"Malcolm Gordon","price":745},{"name":"Muhammad Mokaev","price":-1250}]}]},{"key":"betfair","title":"Betfair","last_update":"2022-10-21T23:52:00Z","markets":[{"key":"h2h","last_update":"2022-10-21T23:52:00Z","outcomes":[{"name":"Malcolm Gordon","price":1000},{"name":"Muhammad Mokaev","price":-1111}]},{"key":"h2h_lay","last_update":"2022-10-21T23:52:00Z","outcomes":[{"name":"Malcolm Gordon","price":1150},{"name":"Muhammad Mokaev","price":-1000}]}]},{"key":"barstool","title":"Barstool Sportsbook","last_update":"2022-10-21T23:54:23Z","markets":[{"key":"h2h","last_update":"2022-10-21T23:54:23Z","outcomes":[{"name":"Malcolm Gordon","price":750},{"name":"Muhammad Mokaev","price":-1250}]}]},{"key":"sugarhouse","title":"SugarHouse","last_update":"2022-10-21T23:53:38Z","markets":[{"key":"h2h","last_update":"2022-10-21T23:53:38Z","outcomes":[{"name":"Malcolm Gordon","price":750},{"name":"Muhammad Mokaev","price":-1250}]}]},{"key":"betrivers","title":"BetRivers","last_update":"2022-10-21T23:54:25Z","markets":[{"key":"h2h","last_update":"2022-10-21T23:54:25Z","outcomes":[{"name":"Malcolm Gordon","price":750},{"name":"Muhammad Mokaev","price":-1250}]}]},{"key":"twinspires","title":"TwinSpires","last_update":"2022-10-21T23:54:23Z","markets":[{"key":"h2h","last_update":"2022-10-21T23:54:23Z","outcomes":[{"name":"Malcolm Gordon","price":750},{"name":"Muhammad Mokaev","price":-1250}]}]},{"key":"lowvig","title":"LowVig.ag","last_update":"2022-10-21T23:53:47Z","markets":[{"key":"h2h","last_update":"2022-10-21T23:53:46Z","outcomes":[{"name":"Malcolm Gordon","price":850},{"name":"Muhammad Mokaev","price":-1299}]}]},{"key":"betmgm","title":"BetMGM","last_update":"2022-10-21T23:54:22Z","markets":[{"key":"h2h","last_update":"2022-10-21T23:54:22Z","outcomes":[{"name":"Malcolm Gordon","price":775},{"name":"Muhammad Mokaev","price":-1400}]}]},{"key":"superbook","title":"SuperBook","last_update":"2022-10-21T23:54:23Z","markets":[{"key":"h2h","last_update":"2022-10-21T23:54:23Z","outcomes":[{"name":"Malcolm Gordon","price":800},{"name":"Muhammad Mokaev","price":-1400}]}]},{"key":"bovada","title":"Bovada","last_update":"2022-10-21T23:55:16Z","markets":[{"key":"h2h","last_update":"2022-10-21T23:55:16Z","outcomes":[{"name":"Malcolm Gordon","price":775},{"name":"Muhammad Mokaev","price":-1400}]}]},{"key":"unibet_us","title":"Unibet","last_update":"2022-10-21T23:53:39Z","markets":[{"key":"h2h","last_update":"2022-10-21T23:53:39Z","outcomes":[{"name":"Malcolm Gordon","price":750},{"name":"Muhammad Mokaev","price":-1250}]}]}]},{"id":"103f24f6b8e8d065556fa8bf7b8ecf1f","sport_key":"mma_mixed_martial_arts","sport_title":"MMA","commence_time":"2022-10-22T15:15:00Z","home_team":"Armen Petrosyan","away_team":"Aj Dobson","bookmakers":[{"key":"betonlineag","title":"BetOnline.ag","last_update":"2022-10-21T23:52:00Z","markets":[{"key":"h2h","last_update":"2022-10-21T23:51:59Z","outcomes":[{"name":"Aj Dobson","price":170},{"name":"Armen Petrosyan","price":-200}]}]},{"key":"draftkings","title":"DraftKings","last_update":"2022-10-21T23:51:10Z","markets":[{"key":"h2h","last_update":"2022-10-21T23:51:10Z","outcomes":[{"name":"Aj Dobson","price":175},{"name":"Armen Petrosyan","price":-205}]}]},{"key":"wynnbet","title":"WynnBET","last_update":"2022-10-21T23:53:38Z","markets":[{"key":"h2h","last_update":"2022-10-21T23:53:38Z","outcomes":[{"name":"Aj Dobson","price":175},{"name":"Armen Petrosyan","price":-213}]}]},{"key":"williamhill_us","title":"William Hill (US)","last_update":"2022-10-21T23:52:52Z","markets":[{"key":"h2h","last_update":"2022-10-21T23:52:52Z","outcomes":[{"name":"Aj Dobson","price":180},{"name":"Armen Petrosyan","price":-220}]}]},{"key":"betfair","title":"Betfair","last_update":"2022-10-21T23:52:00Z","markets":[{"key":"h2h","last_update":"2022-10-21T23:52:00Z","outcomes":[{"name":"Aj Dobson","price":192},{"name":"Armen Petrosyan","price":-200}]},{"key":"h2h_lay","last_update":"2022-10-21T23:52:00Z","outcomes":[{"name":"Aj Dobson","price":200},{"name":"Armen Petrosyan","price":-192}]}]},{"key":"twinspires","title":"TwinSpires","last_update":"2022-10-21T23:54:23Z","markets":[{"key":"h2h","last_update":"2022-10-21T23:54:23Z","outcomes":[{"name":"Aj Dobson","price":165},{"name":"Armen Petrosyan","price":-210}]}]},{"key":"barstool","title":"Barstool Sportsbook","last_update":"2022-10-21T23:54:23Z","markets":[{"key":"h2h","last_update":"2022-10-21T23:54:23Z","outcomes":[{"name":"Aj Dobson","price":165},{"name":"Armen Petrosyan","price":-210}]}]},{"key":"sugarhouse","title":"SugarHouse","last_update":"2022-10-21T23:53:38Z","markets":[{"key":"h2h","last_update":"2022-10-21T23:53:38Z","outcomes":[{"name":"Aj Dobson","price":165},{"name":"Armen Petrosyan","price":-210}]}]},{"key":"betrivers","title":"BetRivers","last_update":"2022-10-21T23:54:25Z","markets":[{"key":"h2h","last_update":"2022-10-21T23:54:25Z","outcomes":[{"name":"Aj Dobson","price":165},{"name":"Armen Petrosyan","price":-210}]}]},{"key":"mybookieag","title":"MyBookie.ag","last_update":"2022-10-21T23:48:51Z","markets":[{"key":"h2h","last_update":"2022-10-21T23:48:51Z","outcomes":[{"name":"Aj Dobson","price":168},{"name":"Armen Petrosyan","price":-217}]}]},{"key":"lowvig","title":"LowVig.ag","last_update":"2022-10-21T23:53:47Z","markets":[{"key":"h2h","last_update":"2022-10-21T23:53:46Z","outcomes":[{"name":"Aj Dobson","price":170},{"name":"Armen Petrosyan","price":-200}]}]},{"key":"betmgm","title":"BetMGM","last_update":"2022-10-21T23:54:22Z","markets":[{"key":"h2h","last_update":"2022-10-21T23:54:22Z","outcomes":[{"name":"Aj Dobson","price":165},{"name":"Armen Petrosyan","price":-210}]}]},{"key":"superbook","title":"SuperBook","last_update":"2022-10-21T23:54:23Z","markets":[{"key":"h2h","last_update":"2022-10-21T23:54:23Z","outcomes":[{"name":"Aj Dobson","price":180},{"name":"Armen Petrosyan","price":-210}]}]},{"key":"bovada","title":"Bovada","last_update":"2022-10-21T23:55:16Z","markets":[{"key":"h2h","last_update":"2022-10-21T23:55:16Z","outcomes":[{"name":"Aj Dobson","price":173},{"name":"Armen Petrosyan","price":-213}]}]},{"key":"unibet_us","title":"Unibet","last_update":"2022-10-21T23:53:39Z","markets":[{"key":"h2h","last_update":"2022-10-21T23:53:39Z","outcomes":[{"name":"Aj Dobson","price":165},{"name":"Armen Petrosyan","price":-210}]}]}]},{"id":"5978fc40db6cdcd5e66e37c64ea8a8bb","sport_key":"mma_mixed_martial_arts","sport_title":"MMA","commence_time":"2022-10-22T16:00:00Z","home_team":"Belal Muhammad","away_team":"Sean Brady","bookmakers":[{"key":"betonlineag","title":"BetOnline.ag","last_update":"2022-10-21T23:52:00Z","markets":[{"key":"h2h","last_update":"2022-10-21T23:51:59Z","outcomes":[{"name":"Belal Muhammad","price":125},{"name":"Sean Brady","price":-145}]}]},{"key":"fanduel","title":"FanDuel","last_update":"2022-10-21T23:51:11Z","markets":[{"key":"h2h","last_update":"2022-10-21T23:51:11Z","outcomes":[{"name":"Belal Muhammad","price":118},{"name":"Sean Brady","price":-144}]}]},{"key":"lowvig","title":"LowVig.ag","last_update":"2022-10-21T23:53:47Z","markets":[{"key":"h2h","last_update":"2022-10-21T23:53:46Z","outcomes":[{"name":"Belal Muhammad","price":125},{"name":"Sean Brady","price":-145}]}]},{"key":"twinspires","title":"TwinSpires","last_update":"2022-10-21T23:54:23Z","markets":[{"key":"h2h","last_update":"2022-10-21T23:54:23Z","outcomes":[{"name":"Belal Muhammad","price":123},{"name":"Sean Brady","price":-152}]}]},{"key":"sugarhouse","title":"SugarHouse","last_update":"2022-10-21T23:53:38Z","markets":[{"key":"h2h","last_update":"2022-10-21T23:53:38Z","outcomes":[{"name":"Belal Muhammad","price":123},{"name":"Sean Brady","price":-152}]}]},{"key":"barstool","title":"Barstool Sportsbook","last_update":"2022-10-21T23:54:23Z","markets":[{"key":"h2h","last_update":"2022-10-21T23:54:23Z","outcomes":[{"name":"Belal Muhammad","price":123},{"name":"Sean Brady","price":-152}]}]},{"key":"betrivers","title":"BetRivers","last_update":"2022-10-21T23:54:25Z","markets":[{"key":"h2h","last_update":"2022-10-21T23:54:25Z","outcomes":[{"name":"Belal Muhammad","price":123},{"name":"Sean Brady","price":-152}]}]},{"key":"draftkings","title":"DraftKings","last_update":"2022-10-21T23:51:10Z","markets":[{"key":"h2h","last_update":"2022-10-21T23:51:10Z","outcomes":[{"name":"Belal Muhammad","price":125},{"name":"Sean Brady","price":-145}]}]},{"key":"williamhill_us","title":"William Hill (US)","last_update":"2022-10-21T23:52:52Z","markets":[{"key":"h2h","last_update":"2022-10-21T23:52:52Z","outcomes":[{"name":"Belal Muhammad","price":120},{"name":"Sean Brady","price":-140}]}]},{"key":"betmgm","title":"BetMGM","last_update":"2022-10-21T23:54:22Z","markets":[{"key":"h2h","last_update":"2022-10-21T23:54:22Z","outcomes":[{"name":"Belal Muhammad","price":115},{"name":"Sean Brady","price":-140}]}]},{"key":"mybookieag","title":"MyBookie.ag","last_update":"2022-10-21T23:48:51Z","markets":[{"key":"h2h","last_update":"2022-10-21T23:48:51Z","outcomes":[{"name":"Belal Muhammad","price":118},{"name":"Sean Brady","price":-149}]}]},{"key":"wynnbet","title":"WynnBET","last_update":"2022-10-21T23:53:38Z","markets":[{"key":"h2h","last_update":"2022-10-21T23:53:38Z","outcomes":[{"name":"Belal Muhammad","price":120},{"name":"Sean Brady","price":-141}]}]},{"key":"betfair","title":"Betfair","last_update":"2022-10-21T23:52:00Z","markets":[{"key":"h2h","last_update":"2022-10-21T23:52:00Z","outcomes":[{"name":"Belal Muhammad","price":124},{"name":"Sean Brady","price":-128}]},{"key":"h2h_lay","last_update":"2022-10-21T23:52:00Z","outcomes":[{"name":"Belal Muhammad","price":130},{"name":"Sean Brady","price":-125}]}]},{"key":"superbook","title":"SuperBook","last_update":"2022-10-21T23:54:23Z","markets":[{"key":"h2h","last_update":"2022-10-21T23:54:23Z","outcomes":[{"name":"Belal Muhammad","price":125},{"name":"Sean Brady","price":-145}]}]},{"key":"bovada","title":"Bovada","last_update":"2022-10-21T23:55:16Z","markets":[{"key":"h2h","last_update":"2022-10-21T23:55:16Z","outcomes":[{"name":"Belal Muhammad","price":115},{"name":"Sean Brady","price":-140}]}]},{"key":"unibet_us","title":"Unibet","last_update":"2022-10-21T23:53:39Z","markets":[{"key":"h2h","last_update":"2022-10-21T23:53:39Z","outcomes":[{"name":"Belal Muhammad","price":123},{"name":"Sean Brady","price":-152}]}]}]},{"id":"ce548bb2ec54f5aa739d8e0824e15176","sport_key":"mma_mixed_martial_arts","sport_title":"MMA","commence_time":"2022-10-22T16:15:00Z","home_team":"Gadzhi Omargadzhiev","away_team":"Abubakar Nurmagomedov","bookmakers":[{"key":"fanduel","title":"FanDuel","last_update":"2022-10-21T23:51:11Z","markets":[{"key":"h2h","last_update":"2022-10-21T23:51:11Z","outcomes":[{"name":"Abubakar Nurmagomedov","price":-176},{"name":"Gadzhi Omargadzhiev","price":142}]}]},{"key":"betonlineag","title":"BetOnline.ag","last_update":"2022-10-21T23:52:00Z","markets":[{"key":"h2h","last_update":"2022-10-21T23:51:59Z","outcomes":[{"name":"Abubakar Nurmagomedov","price":-161},{"name":"Gadzhi Omargadzhiev","price":140}]}]},{"key":"draftkings","title":"DraftKings","last_update":"2022-10-21T23:51:10Z","markets":[{"key":"h2h","last_update":"2022-10-21T23:51:10Z","outcomes":[{"name":"Abubakar Nurmagomedov","price":-165},{"name":"Gadzhi Omargadzhiev","price":140}]}]},{"key":"mybookieag","title":"MyBookie.ag","last_update":"2022-10-21T23:48:51Z","markets":[{"key":"h2h","last_update":"2022-10-21T23:48:51Z","outcomes":[{"name":"Abubakar Nurmagomedov","price":-175},{"name":"Gadzhi Omargadzhiev","price":136}]}]},{"key":"wynnbet","title":"WynnBET","last_update":"2022-10-21T23:53:38Z","markets":[{"key":"h2h","last_update":"2022-10-21T23:53:38Z","outcomes":[{"name":"Abubakar Nurmagomedov","price":-164},{"name":"Gadzhi Omargadzhiev","price":140}]}]},{"key":"williamhill_us","title":"William Hill (US)","last_update":"2022-10-21T23:52:52Z","markets":[{"key":"h2h","last_update":"2022-10-21T23:52:52Z","outcomes":[{"name":"Abubakar Nurmagomedov","price":-165},{"name":"Gadzhi Omargadzhiev","price":140}]}]},{"key":"betfair","title":"Betfair","last_update":"2022-10-21T23:52:00Z","markets":[{"key":"h2h","last_update":"2022-10-21T23:52:00Z","outcomes":[{"name":"Abubakar Nurmagomedov","price":-159},{"name":"Gadzhi Omargadzhiev","price":150}]},{"key":"h2h_lay","last_update":"2022-10-21T23:52:00Z","outcomes":[{"name":"Abubakar Nurmagomedov","price":-152},{"name":"Gadzhi Omargadzhiev","price":160}]}]},{"key":"barstool","title":"Barstool Sportsbook","last_update":"2022-10-21T23:54:23Z","markets":[{"key":"h2h","last_update":"2022-10-21T23:54:23Z","outcomes":[{"name":"Abubakar Nurmagomedov","price":-175},{"name":"Gadzhi Omargadzhiev","price":140}]}]},{"key":"sugarhouse","title":"SugarHouse","last_update":"2022-10-21T23:53:38Z","markets":[{"key":"h2h","last_update":"2022-10-21T23:53:38Z","outcomes":[{"name":"Abubakar Nurmagomedov","price":-175},{"name":"Gadzhi Omargadzhiev","price":140}]}]},{"key":"betrivers","title":"BetRivers","last_update":"2022-10-21T23:54:25Z","markets":[{"key":"h2h","last_update":"2022-10-21T23:54:25Z","outcomes":[{"name":"Abubakar Nurmagomedov","price":-175},{"name":"Gadzhi Omargadzhiev","price":140}]}]},{"key":"twinspires","title":"TwinSpires","last_update":"2022-10-21T23:54:23Z","markets":[{"key":"h2h","last_update":"2022-10-21T23:54:23Z","outcomes":[{"name":"Abubakar Nurmagomedov","price":-175},{"name":"Gadzhi Omargadzhiev","price":140}]}]},{"key":"lowvig","title":"LowVig.ag","last_update":"2022-10-21T23:53:47Z","markets":[{"key":"h2h","last_update":"2022-10-21T23:53:46Z","outcomes":[{"name":"Abubakar Nurmagomedov","price":-160},{"name":"Gadzhi Omargadzhiev","price":140}]}]},{"key":"betmgm","title":"BetMGM","last_update":"2022-10-21T23:54:22Z","markets":[{"key":"h2h","last_update":"2022-10-21T23:54:22Z","outcomes":[{"name":"Abubakar Nurmagomedov","price":-165},{"name":"Gadzhi Omargadzhiev","price":135}]}]},{"key":"superbook","title":"SuperBook","last_update":"2022-10-21T23:54:23Z","markets":[{"key":"h2h","last_update":"2022-10-21T23:54:23Z","outcomes":[{"name":"Abubakar Nurmagomedov","price":-165},{"name":"Gadzhi Omargadzhiev","price":145}]}]},{"key":"bovada","title":"Bovada","last_update":"2022-10-21T23:55:16Z","markets":[{"key":"h2h","last_update":"2022-10-21T23:55:16Z","outcomes":[{"name":"Abubakar Nurmagomedov","price":-180},{"name":"Gadzhi Omargadzhiev","price":145}]}]},{"key":"unibet_us","title":"Unibet","last_update":"2022-10-21T23:53:39Z","markets":[{"key":"h2h","last_update":"2022-10-21T23:53:39Z","outcomes":[{"name":"Abubakar Nurmagomedov","price":-175},{"name":"Gadzhi Omargadzhiev","price":140}]}]}]},{"id":"a7152668b0f75ea2b4f1e1e789f2dfb4","sport_key":"mma_mixed_martial_arts","sport_title":"MMA","commence_time":"2022-10-22T16:45:00Z","home_team":"Volkan Oezdemir","away_team":"Nikita Krylov","bookmakers":[{"key":"fanduel","title":"FanDuel","last_update":"2022-10-21T23:51:11Z","markets":[{"key":"h2h","last_update":"2022-10-21T23:51:11Z","outcomes":[{"name":"Nikita Krylov","price":-188},{"name":"Volkan Oezdemir","price":152}]}]},{"key":"mybookieag","title":"MyBookie.ag","last_update":"2022-10-21T23:48:51Z","markets":[{"key":"h2h","last_update":"2022-10-21T23:48:51Z","outcomes":[{"name":"Nikita Krylov","price":-192},{"name":"Volkan Oezdemir","price":148}]}]},{"key":"wynnbet","title":"WynnBET","last_update":"2022-10-21T23:53:38Z","markets":[{"key":"h2h","last_update":"2022-10-21T23:53:38Z","outcomes":[{"name":"Nikita Krylov","price":-179},{"name":"Volkan Oezdemir","price":150}]}]},{"key":"williamhill_us","title":"William Hill (US)","last_update":"2022-10-21T23:52:52Z","markets":[{"key":"h2h","last_update":"2022-10-21T23:52:52Z","outcomes":[{"name":"Nikita Krylov","price":-170},{"name":"Volkan Oezdemir","price":145}]}]},{"key":"betfair","title":"Betfair","last_update":"2022-10-21T23:52:00Z","markets":[{"key":"h2h","last_update":"2022-10-21T23:52:00Z","outcomes":[{"name":"Nikita Krylov","price":-172},{"name":"Volkan Oezdemir","price":168}]},{"key":"h2h_lay","last_update":"2022-10-21T23:52:00Z","outcomes":[{"name":"Nikita Krylov","price":-167},{"name":"Volkan Oezdemir","price":172}]}]},{"key":"barstool","title":"Barstool Sportsbook","last_update":"2022-10-21T23:54:23Z","markets":[{"key":"h2h","last_update":"2022-10-21T23:54:23Z","outcomes":[{"name":"Nikita Krylov","price":-180},{"name":"Volkan Oezdemir","price":143}]}]},{"key":"sugarhouse","title":"SugarHouse","last_update":"2022-10-21T23:53:38Z","markets":[{"key":"h2h","last_update":"2022-10-21T23:53:38Z","outcomes":[{"name":"Nikita Krylov","price":-180},{"name":"Volkan Oezdemir","price":143}]}]},{"key":"betrivers","title":"BetRivers","last_update":"2022-10-21T23:54:25Z","markets":[{"key":"h2h","last_update":"2022-10-21T23:54:25Z","outcomes":[{"name":"Nikita Krylov","price":-180},{"name":"Volkan Oezdemir","price":143}]}]},{"key":"twinspires","title":"TwinSpires","last_update":"2022-10-21T23:54:23Z","markets":[{"key":"h2h","last_update":"2022-10-21T23:54:23Z","outcomes":[{"name":"Nikita Krylov","price":-180},{"name":"Volkan Oezdemir","price":143}]}]},{"key":"betonlineag","title":"BetOnline.ag","last_update":"2022-10-21T23:52:00Z","markets":[{"key":"h2h","last_update":"2022-10-21T23:51:59Z","outcomes":[{"name":"Nikita Krylov","price":-179},{"name":"Volkan Oezdemir","price":152}]}]},{"key":"draftkings","title":"DraftKings","last_update":"2022-10-21T23:51:10Z","markets":[{"key":"h2h","last_update":"2022-10-21T23:51:10Z","outcomes":[{"name":"Nikita Krylov","price":-175},{"name":"Volkan Oezdemir","price":150}]}]},{"key":"lowvig","title":"LowVig.ag","last_update":"2022-10-21T23:53:47Z","markets":[{"key":"h2h","last_update":"2022-10-21T23:53:46Z","outcomes":[{"name":"Nikita Krylov","price":-177},{"name":"Volkan Oezdemir","price":152}]}]},{"key":"betmgm","title":"BetMGM","last_update":"2022-10-21T23:54:22Z","markets":[{"key":"h2h","last_update":"2022-10-21T23:54:22Z","outcomes":[{"name":"Nikita Krylov","price":-185},{"name":"Volkan Oezdemir","price":150}]}]},{"key":"superbook","title":"SuperBook","last_update":"2022-10-21T23:54:23Z","markets":[{"key":"h2h","last_update":"2022-10-21T23:54:23Z","outcomes":[{"name":"Nikita Krylov","price":-180},{"name":"Volkan Oezdemir","price":160}]}]},{"key":"bovada","title":"Bovada","last_update":"2022-10-21T23:55:16Z","markets":[{"key":"h2h","last_update":"2022-10-21T23:55:16Z","outcomes":[{"name":"Nikita Krylov","price":-185},{"name":"Volkan Oezdemir","price":150}]}]},{"key":"unibet_us","title":"Unibet","last_update":"2022-10-21T23:53:39Z","markets":[{"key":"h2h","last_update":"2022-10-21T23:53:39Z","outcomes":[{"name":"Nikita Krylov","price":-180},{"name":"Volkan Oezdemir","price":143}]}]}]},{"id":"17ce6c1c93620bb35373b5fb01bb7dad","sport_key":"mma_mixed_martial_arts","sport_title":"MMA","commence_time":"2022-10-22T17:15:00Z","home_team":"Makhmud Muradov","away_team":"Caio Borralho","bookmakers":[{"key":"fanduel","title":"FanDuel","last_update":"2022-10-21T23:51:11Z","markets":[{"key":"h2h","last_update":"2022-10-21T23:51:11Z","outcomes":[{"name":"Caio Borralho","price":-230},{"name":"Makhmud Muradov","price":184}]}]},{"key":"betonlineag","title":"BetOnline.ag","last_update":"2022-10-21T23:52:00Z","markets":[{"key":"h2h","last_update":"2022-10-21T23:51:59Z","outcomes":[{"name":"Caio Borralho","price":-200},{"name":"Makhmud Muradov","price":170}]}]},{"key":"mybookieag","title":"MyBookie.ag","last_update":"2022-10-21T23:48:51Z","markets":[{"key":"h2h","last_update":"2022-10-21T23:48:51Z","outcomes":[{"name":"Caio Borralho","price":-222},{"name":"Makhmud Muradov","price":170}]}]},{"key":"draftkings","title":"DraftKings","last_update":"2022-10-21T23:51:10Z","markets":[{"key":"h2h","last_update":"2022-10-21T23:51:10Z","outcomes":[{"name":"Caio Borralho","price":-200},{"name":"Makhmud Muradov","price":170}]}]},{"key":"wynnbet","title":"WynnBET","last_update":"2022-10-21T23:53:38Z","markets":[{"key":"h2h","last_update":"2022-10-21T23:53:38Z","outcomes":[{"name":"Caio Borralho","price":-213},{"name":"Makhmud Muradov","price":175}]}]},{"key":"betfair","title":"Betfair","last_update":"2022-10-21T23:52:00Z","markets":[{"key":"h2h","last_update":"2022-10-21T23:52:00Z","outcomes":[{"name":"Caio Borralho","price":-208},{"name":"Makhmud Muradov","price":200}]},{"key":"h2h_lay","last_update":"2022-10-21T23:52:00Z","outcomes":[{"name":"Caio Borralho","price":-204},{"name":"Makhmud Muradov","price":210}]}]},{"key":"barstool","title":"Barstool Sportsbook","last_update":"2022-10-21T23:54:23Z","markets":[{"key":"h2h","last_update":"2022-10-21T23:54:23Z","outcomes":[{"name":"Caio Borralho","price":-215},{"name":"Makhmud Muradov","price":170}]}]},{"key":"sugarhouse","title":"SugarHouse","last_update":"2022-10-21T23:53:38Z","markets":[{"key":"h2h","last_update":"2022-10-21T23:53:38Z","outcomes":[{"name":"Caio Borralho","price":-215},{"name":"Makhmud Muradov","price":170}]}]},{"key":"betrivers","title":"BetRivers","last_update":"2022-10-21T23:54:25Z","markets":[{"key":"h2h","last_update":"2022-10-21T23:54:25Z","outcomes":[{"name":"Caio Borralho","price":-215},{"name":"Makhmud Muradov","price":170}]}]},{"key":"twinspires","title":"TwinSpires","last_update":"2022-10-21T23:54:23Z","markets":[{"key":"h2h","last_update":"2022-10-21T23:54:23Z","outcomes":[{"name":"Caio Borralho","price":-215},{"name":"Makhmud Muradov","price":170}]}]},{"key":"lowvig","title":"LowVig.ag","last_update":"2022-10-21T23:53:47Z","markets":[{"key":"h2h","last_update":"2022-10-21T23:53:46Z","outcomes":[{"name":"Caio Borralho","price":-200},{"name":"Makhmud Muradov","price":170}]}]},{"key":"williamhill_us","title":"William Hill (US)","last_update":"2022-10-21T23:52:52Z","markets":[{"key":"h2h","last_update":"2022-10-21T23:52:52Z","outcomes":[{"name":"Caio Borralho","price":-200},{"name":"Makhmud Muradov","price":170}]}]},{"key":"betmgm","title":"BetMGM","last_update":"2022-10-21T23:54:22Z","markets":[{"key":"h2h","last_update":"2022-10-21T23:54:22Z","outcomes":[{"name":"Caio Borralho","price":-210},{"name":"Makhmud Muradov","price":165}]}]},{"key":"superbook","title":"SuperBook","last_update":"2022-10-21T23:54:23Z","markets":[{"key":"h2h","last_update":"2022-10-21T23:54:23Z","outcomes":[{"name":"Caio Borralho","price":-210},{"name":"Makhmud Muradov","price":180}]}]},{"key":"bovada","title":"Bovada","last_update":"2022-10-21T23:55:16Z","markets":[{"key":"h2h","last_update":"2022-10-21T23:55:16Z","outcomes":[{"name":"Caio Borralho","price":-230},{"name":"Makhmud Muradov","price":174}]}]},{"key":"unibet_us","title":"Unibet","last_update":"2022-10-21T23:53:39Z","markets":[{"key":"h2h","last_update":"2022-10-21T23:53:39Z","outcomes":[{"name":"Caio Borralho","price":-215},{"name":"Makhmud Muradov","price":170}]}]}]},{"id":"bb8ad208f78f78762a462d78e595a2e6","sport_key":"mma_mixed_martial_arts","sport_title":"MMA","commence_time":"2022-10-22T18:15:00Z","home_team":"Manon Fiorot","away_team":"Katlyn Chookagian","bookmakers":[{"key":"fanduel","title":"FanDuel","last_update":"2022-10-21T23:51:11Z","markets":[{"key":"h2h","last_update":"2022-10-21T23:51:11Z","outcomes":[{"name":"Katlyn Chookagian","price":194},{"name":"Manon Fiorot","price":-245}]}]},{"key":"betonlineag","title":"BetOnline.ag","last_update":"2022-10-21T23:52:00Z","markets":[{"key":"h2h","last_update":"2022-10-21T23:51:59Z","outcomes":[{"name":"Katlyn Chookagian","price":187},{"name":"Manon Fiorot","price":-217}]}]},{"key":"mybookieag","title":"MyBookie.ag","last_update":"2022-10-21T23:48:51Z","markets":[{"key":"h2h","last_update":"2022-10-21T23:48:51Z","outcomes":[{"name":"Katlyn Chookagian","price":170},{"name":"Manon Fiorot","price":-222}]}]},{"key":"draftkings","title":"DraftKings","last_update":"2022-10-21T23:51:10Z","markets":[{"key":"h2h","last_update":"2022-10-21T23:51:10Z","outcomes":[{"name":"Katlyn Chookagian","price":180},{"name":"Manon Fiorot","price":-210}]}]},{"key":"wynnbet","title":"WynnBET","last_update":"2022-10-21T23:53:38Z","markets":[{"key":"h2h","last_update":"2022-10-21T23:53:38Z","outcomes":[{"name":"Katlyn Chookagian","price":175},{"name":"Manon Fiorot","price":-213}]}]},{"key":"betfair","title":"Betfair","last_update":"2022-10-21T23:52:00Z","markets":[{"key":"h2h","last_update":"2022-10-21T23:52:00Z","outcomes":[{"name":"Katlyn Chookagian","price":210},{"name":"Manon Fiorot","price":-217}]},{"key":"h2h_lay","last_update":"2022-10-21T23:52:00Z","outcomes":[{"name":"Katlyn Chookagian","price":220},{"name":"Manon Fiorot","price":-208}]}]},{"key":"betmgm","title":"BetMGM","last_update":"2022-10-21T23:54:22Z","markets":[{"key":"h2h","last_update":"2022-10-21T23:54:22Z","outcomes":[{"name":"Katlyn Chookagian","price":190},{"name":"Manon Fiorot","price":-250}]}]},{"key":"lowvig","title":"LowVig.ag","last_update":"2022-10-21T23:53:47Z","markets":[{"key":"h2h","last_update":"2022-10-21T23:53:46Z","outcomes":[{"name":"Katlyn Chookagian","price":187},{"name":"Manon Fiorot","price":-217}]}]},{"key":"barstool","title":"Barstool Sportsbook","last_update":"2022-10-21T23:54:23Z","markets":[{"key":"h2h","last_update":"2022-10-21T23:54:23Z","outcomes":[{"name":"Katlyn Chookagian","price":175},{"name":"Manon Fiorot","price":-225}]}]},{"key":"sugarhouse","title":"SugarHouse","last_update":"2022-10-21T23:53:38Z","markets":[{"key":"h2h","last_update":"2022-10-21T23:53:38Z","outcomes":[{"name":"Katlyn Chookagian","price":175},{"name":"Manon Fiorot","price":-225}]}]},{"key":"betrivers","title":"BetRivers","last_update":"2022-10-21T23:54:25Z","markets":[{"key":"h2h","last_update":"2022-10-21T23:54:25Z","outcomes":[{"name":"Katlyn Chookagian","price":175},{"name":"Manon Fiorot","price":-225}]}]},{"key":"twinspires","title":"TwinSpires","last_update":"2022-10-21T23:54:23Z","markets":[{"key":"h2h","last_update":"2022-10-21T23:54:23Z","outcomes":[{"name":"Katlyn Chookagian","price":175},{"name":"Manon Fiorot","price":-225}]}]},{"key":"williamhill_us","title":"William Hill (US)","last_update":"2022-10-21T23:52:52Z","markets":[{"key":"h2h","last_update":"2022-10-21T23:52:52Z","outcomes":[{"name":"Katlyn Chookagian","price":180},{"name":"Manon Fiorot","price":-220}]}]},{"key":"superbook","title":"SuperBook","last_update":"2022-10-21T23:54:23Z","markets":[{"key":"h2h","last_update":"2022-10-21T23:54:23Z","outcomes":[{"name":"Katlyn Chookagian","price":180},{"name":"Manon Fiorot","price":-210}]}]},{"key":"bovada","title":"Bovada","last_update":"2022-10-21T23:55:16Z","markets":[{"key":"h2h","last_update":"2022-10-21T23:55:16Z","outcomes":[{"name":"Katlyn Chookagian","price":175},{"name":"Manon Fiorot","price":-220}]}]},{"key":"unibet_us","title":"Unibet","last_update":"2022-10-21T23:53:39Z","markets":[{"key":"h2h","last_update":"2022-10-21T23:53:39Z","outcomes":[{"name":"Katlyn Chookagian","price":175},{"name":"Manon Fiorot","price":-225}]}]}]},{"id":"d58715e3a819c1c2f5fd197708b72960","sport_key":"mma_mixed_martial_arts","sport_title":"MMA","commence_time":"2022-10-22T18:45:00Z","home_team":"Aljamain Sterling","away_team":"T.J. Dillashaw","bookmakers":[{"key":"fanduel","title":"FanDuel","last_update":"2022-10-21T23:51:11Z","markets":[{"key":"h2h","last_update":"2022-10-21T23:51:11Z","outcomes":[{"name":"Aljamain Sterling","price":-172},{"name":"T.J. Dillashaw","price":140}]}]},{"key":"draftkings","title":"DraftKings","last_update":"2022-10-21T23:51:10Z","markets":[{"key":"h2h","last_update":"2022-10-21T23:51:10Z","outcomes":[{"name":"Aljamain Sterling","price":-175},{"name":"T.J. Dillashaw","price":150}]}]},{"key":"sugarhouse","title":"SugarHouse","last_update":"2022-10-21T23:53:38Z","markets":[{"key":"h2h","last_update":"2022-10-21T23:53:38Z","outcomes":[{"name":"Aljamain Sterling","price":-175},{"name":"T.J. Dillashaw","price":138}]}]},{"key":"twinspires","title":"TwinSpires","last_update":"2022-10-21T23:54:23Z","markets":[{"key":"h2h","last_update":"2022-10-21T23:54:23Z","outcomes":[{"name":"Aljamain Sterling","price":-175},{"name":"T.J. Dillashaw","price":138}]}]},{"key":"betrivers","title":"BetRivers","last_update":"2022-10-21T23:54:25Z","markets":[{"key":"h2h","last_update":"2022-10-21T23:54:25Z","outcomes":[{"name":"Aljamain Sterling","price":-175},{"name":"T.J. Dillashaw","price":138}]}]},{"key":"barstool","title":"Barstool Sportsbook","last_update":"2022-10-21T23:54:23Z","markets":[{"key":"h2h","last_update":"2022-10-21T23:54:23Z","outcomes":[{"name":"Aljamain Sterling","price":-175},{"name":"T.J. Dillashaw","price":138}]}]},{"key":"williamhill_us","title":"William Hill (US)","last_update":"2022-10-21T23:52:52Z","markets":[{"key":"h2h","last_update":"2022-10-21T23:52:52Z","outcomes":[{"name":"Aljamain Sterling","price":-170},{"name":"T.J. Dillashaw","price":145}]}]},{"key":"betfair","title":"Betfair","last_update":"2022-10-21T23:52:00Z","markets":[{"key":"h2h","last_update":"2022-10-21T23:52:00Z","outcomes":[{"name":"Aljamain Sterling","price":-156},{"name":"T.J. Dillashaw","price":154}]},{"key":"h2h_lay","last_update":"2022-10-21T23:52:00Z","outcomes":[{"name":"Aljamain Sterling","price":-154},{"name":"T.J. Dillashaw","price":156}]}]},{"key":"lowvig","title":"LowVig.ag","last_update":"2022-10-21T23:53:47Z","markets":[{"key":"h2h","last_update":"2022-10-21T23:53:46Z","outcomes":[{"name":"Aljamain Sterling","price":-175},{"name":"T.J. Dillashaw","price":150}]}]},{"key":"betonlineag","title":"BetOnline.ag","last_update":"2022-10-21T23:52:00Z","markets":[{"key":"h2h","last_update":"2022-10-21T23:51:59Z","outcomes":[{"name":"Aljamain Sterling","price":-175},{"name":"T.J. Dillashaw","price":150}]}]},{"key":"betmgm","title":"BetMGM","last_update":"2022-10-21T23:54:22Z","markets":[{"key":"h2h","last_update":"2022-10-21T23:54:22Z","outcomes":[{"name":"Aljamain Sterling","price":-165},{"name":"T.J. Dillashaw","price":135}]}]},{"key":"mybookieag","title":"MyBookie.ag","last_update":"2022-10-21T23:48:51Z","markets":[{"key":"h2h","last_update":"2022-10-21T23:48:51Z","outcomes":[{"name":"Aljamain Sterling","price":-185},{"name":"T.J. Dillashaw","price":143}]}]},{"key":"superbook","title":"SuperBook","last_update":"2022-10-21T23:54:23Z","markets":[{"key":"h2h","last_update":"2022-10-21T23:54:23Z","outcomes":[{"name":"Aljamain Sterling","price":-175},{"name":"T.J. Dillashaw","price":155}]}]},{"key":"bovada","title":"Bovada","last_update":"2022-10-21T23:55:16Z","markets":[{"key":"h2h","last_update":"2022-10-21T23:55:16Z","outcomes":[{"name":"Aljamain Sterling","price":-174},{"name":"T.J. Dillashaw","price":140}]}]},{"key":"unibet_us","title":"Unibet","last_update":"2022-10-21T23:53:39Z","markets":[{"key":"h2h","last_update":"2022-10-21T23:53:39Z","outcomes":[{"name":"Aljamain Sterling","price":-175},{"name":"T.J. Dillashaw","price":138}]}]}]},{"id":"e468a4a216908acbe0a29538cce2ab5d","sport_key":"mma_mixed_martial_arts","sport_title":"MMA","commence_time":"2022-10-22T18:45:00Z","home_team":"Mateusz Gamrot","away_team":"Beneil Dariush","bookmakers":[{"key":"fanduel","title":"FanDuel","last_update":"2022-10-21T23:51:11Z","markets":[{"key":"h2h","last_update":"2022-10-21T23:51:11Z","outcomes":[{"name":"Beneil Dariush","price":172},{"name":"Mateusz Gamrot","price":-215}]}]},{"key":"betonlineag","title":"BetOnline.ag","last_update":"2022-10-21T23:52:00Z","markets":[{"key":"h2h","last_update":"2022-10-21T23:51:59Z","outcomes":[{"name":"Beneil Dariush","price":185},{"name":"Mateusz Gamrot","price":-222}]}]},{"key":"mybookieag","title":"MyBookie.ag","last_update":"2022-10-21T23:48:51Z","markets":[{"key":"h2h","last_update":"2022-10-21T23:48:51Z","outcomes":[{"name":"Beneil Dariush","price":173},{"name":"Mateusz Gamrot","price":-227}]}]},{"key":"draftkings","title":"DraftKings","last_update":"2022-10-21T23:51:10Z","markets":[{"key":"h2h","last_update":"2022-10-21T23:51:10Z","outcomes":[{"name":"Beneil Dariush","price":185},{"name":"Mateusz Gamrot","price":-215}]}]},{"key":"wynnbet","title":"WynnBET","last_update":"2022-10-21T23:53:38Z","markets":[{"key":"h2h","last_update":"2022-10-21T23:53:38Z","outcomes":[{"name":"Beneil Dariush","price":165},{"name":"Mateusz Gamrot","price":-200}]}]},{"key":"betfair","title":"Betfair","last_update":"2022-10-21T23:52:00Z","markets":[{"key":"h2h","last_update":"2022-10-21T23:52:00Z","outcomes":[{"name":"Beneil Dariush","price":184},{"name":"Mateusz Gamrot","price":-192}]},{"key":"h2h_lay","last_update":"2022-10-21T23:52:00Z","outcomes":[{"name":"Beneil Dariush","price":198},{"name":"Mateusz Gamrot","price":-182}]}]},{"key":"betmgm","title":"BetMGM","last_update":"2022-10-21T23:54:22Z","markets":[{"key":"h2h","last_update":"2022-10-21T23:54:22Z","outcomes":[{"name":"Beneil Dariush","price":160},{"name":"Mateusz Gamrot","price":-200}]}]},{"key":"lowvig","title":"LowVig.ag","last_update":"2022-10-21T23:53:47Z","markets":[{"key":"h2h","last_update":"2022-10-21T23:53:46Z","outcomes":[{"name":"Beneil Dariush","price":185},{"name":"Mateusz Gamrot","price":-220}]}]},{"key":"barstool","title":"Barstool Sportsbook","last_update":"2022-10-21T23:54:23Z","markets":[{"key":"h2h","last_update":"2022-10-21T23:54:23Z","outcomes":[{"name":"Beneil Dariush","price":160},{"name":"Mateusz Gamrot","price":-200}]}]},{"key":"sugarhouse","title":"SugarHouse","last_update":"2022-10-21T23:53:38Z","markets":[{"key":"h2h","last_update":"2022-10-21T23:53:38Z","outcomes":[{"name":"Beneil Dariush","price":160},{"name":"Mateusz Gamrot","price":-200}]}]},{"key":"betrivers","title":"BetRivers","last_update":"2022-10-21T23:54:25Z","markets":[{"key":"h2h","last_update":"2022-10-21T23:54:25Z","outcomes":[{"name":"Beneil Dariush","price":160},{"name":"Mateusz Gamrot","price":-200}]}]},{"key":"twinspires","title":"TwinSpires","last_update":"2022-10-21T23:54:23Z","markets":[{"key":"h2h","last_update":"2022-10-21T23:54:23Z","outcomes":[{"name":"Beneil Dariush","price":160},{"name":"Mateusz Gamrot","price":-200}]}]},{"key":"williamhill_us","title":"William Hill (US)","last_update":"2022-10-21T23:52:52Z","markets":[{"key":"h2h","last_update":"2022-10-21T23:52:52Z","outcomes":[{"name":"Beneil Dariush","price":170},{"name":"Mateusz Gamrot","price":-200}]}]},{"key":"superbook","title":"SuperBook","last_update":"2022-10-21T23:54:23Z","markets":[{"key":"h2h","last_update":"2022-10-21T23:54:23Z","outcomes":[{"name":"Beneil Dariush","price":185},{"name":"Mateusz Gamrot","price":-215}]}]},{"key":"bovada","title":"Bovada","last_update":"2022-10-21T23:55:16Z","markets":[{"key":"h2h","last_update":"2022-10-21T23:55:16Z","outcomes":[{"name":"Beneil Dariush","price":165},{"name":"Mateusz Gamrot","price":-210}]}]},{"key":"unibet_us","title":"Unibet","last_update":"2022-10-21T23:53:39Z","markets":[{"key":"h2h","last_update":"2022-10-21T23:53:39Z","outcomes":[{"name":"Beneil Dariush","price":160},{"name":"Mateusz Gamrot","price":-200}]}]}]},{"id":"1bb4f927505881b126398d742f517554","sport_key":"mma_mixed_martial_arts","sport_title":"MMA","commence_time":"2022-10-22T19:15:00Z","home_team":"Sean O'Malley","away_team":"Petr Yan","bookmakers":[{"key":"betonlineag","title":"BetOnline.ag","last_update":"2022-10-21T23:52:00Z","markets":[{"key":"h2h","last_update":"2022-10-21T23:51:59Z","outcomes":[{"name":"Petr Yan","price":-278},{"name":"Sean O'Malley","price":235}]}]},{"key":"fanduel","title":"FanDuel","last_update":"2022-10-21T23:51:11Z","markets":[{"key":"h2h","last_update":"2022-10-21T23:51:11Z","outcomes":[{"name":"Petr Yan","price":-290},{"name":"Sean O'Malley","price":225}]}]},{"key":"lowvig","title":"LowVig.ag","last_update":"2022-10-21T23:53:47Z","markets":[{"key":"h2h","last_update":"2022-10-21T23:53:46Z","outcomes":[{"name":"Petr Yan","price":-275},{"name":"Sean O'Malley","price":235}]}]},{"key":"betrivers","title":"BetRivers","last_update":"2022-10-21T23:54:25Z","markets":[{"key":"h2h","last_update":"2022-10-21T23:54:25Z","outcomes":[{"name":"Petr Yan","price":-286},{"name":"Sean O'Malley","price":225}]}]},{"key":"barstool","title":"Barstool Sportsbook","last_update":"2022-10-21T23:54:23Z","markets":[{"key":"h2h","last_update":"2022-10-21T23:54:23Z","outcomes":[{"name":"Petr Yan","price":-286},{"name":"Sean O'Malley","price":225}]}]},{"key":"sugarhouse","title":"SugarHouse","last_update":"2022-10-21T23:53:38Z","markets":[{"key":"h2h","last_update":"2022-10-21T23:53:38Z","outcomes":[{"name":"Petr Yan","price":-286},{"name":"Sean O'Malley","price":225}]}]},{"key":"draftkings","title":"DraftKings","last_update":"2022-10-21T23:51:10Z","markets":[{"key":"h2h","last_update":"2022-10-21T23:51:10Z","outcomes":[{"name":"Petr Yan","price":-275},{"name":"Sean O'Malley","price":230}]}]},{"key":"twinspires","title":"TwinSpires","last_update":"2022-10-21T23:54:23Z","markets":[{"key":"h2h","last_update":"2022-10-21T23:54:23Z","outcomes":[{"name":"Petr Yan","price":-286},{"name":"Sean O'Malley","price":225}]}]},{"key":"williamhill_us","title":"William Hill (US)","last_update":"2022-10-21T23:52:52Z","markets":[{"key":"h2h","last_update":"2022-10-21T23:52:52Z","outcomes":[{"name":"Petr Yan","price":-280},{"name":"Sean O'Malley","price":230}]}]},{"key":"betmgm","title":"BetMGM","last_update":"2022-10-21T23:54:22Z","markets":[{"key":"h2h","last_update":"2022-10-21T23:54:22Z","outcomes":[{"name":"Petr Yan","price":-275},{"name":"Sean O'Malley","price":220}]}]},{"key":"mybookieag","title":"MyBookie.ag","last_update":"2022-10-21T23:48:51Z","markets":[{"key":"h2h","last_update":"2022-10-21T23:48:51Z","outcomes":[{"name":"Petr Yan","price":-285},{"name":"Sean O'Malley","price":211}]}]},{"key":"superbook","title":"SuperBook","last_update":"2022-10-21T23:54:23Z","markets":[{"key":"h2h","last_update":"2022-10-21T23:54:23Z","outcomes":[{"name":"Petr Yan","price":-275},{"name":"Sean O'Malley","price":235}]}]},{"key":"betfair","title":"Betfair","last_update":"2022-10-21T23:52:00Z","markets":[{"key":"h2h","last_update":"2022-10-21T23:52:00Z","outcomes":[{"name":"Petr Yan","price":-270},{"name":"Sean O'Malley","price":260}]},{"key":"h2h_lay","last_update":"2022-10-21T23:52:00Z","outcomes":[{"name":"Petr Yan","price":-263},{"name":"Sean O'Malley","price":275}]}]},{"key":"wynnbet","title":"WynnBET","last_update":"2022-10-21T23:53:38Z","markets":[{"key":"h2h","last_update":"2022-10-21T23:53:38Z","outcomes":[{"name":"Petr Yan","price":-278},{"name":"Sean O'Malley","price":220}]}]},{"key":"bovada","title":"Bovada","last_update":"2022-10-21T23:55:16Z","markets":[{"key":"h2h","last_update":"2022-10-21T23:55:16Z","outcomes":[{"name":"Petr Yan","price":-265},{"name":"Sean O'Malley","price":215}]}]},{"key":"unibet_us","title":"Unibet","last_update":"2022-10-21T23:53:39Z","markets":[{"key":"h2h","last_update":"2022-10-21T23:53:39Z","outcomes":[{"name":"Petr Yan","price":-286},{"name":"Sean O'Malley","price":225}]}]}]},{"id":"06764663decd52fa663d604dfd65e955","sport_key":"mma_mixed_martial_arts","sport_title":"MMA","commence_time":"2022-10-22T20:30:00Z","home_team":"Islam Makhachev","away_team":"Charles Oliveira","bookmakers":[{"key":"fanduel","title":"FanDuel","last_update":"2022-10-21T23:51:11Z","markets":[{"key":"h2h","last_update":"2022-10-21T23:51:11Z","outcomes":[{"name":"Charles Oliveira","price":140},{"name":"Islam Makhachev","price":-172}]}]},{"key":"lowvig","title":"LowVig.ag","last_update":"2022-10-21T23:53:47Z","markets":[{"key":"h2h","last_update":"2022-10-21T23:53:46Z","outcomes":[{"name":"Charles Oliveira","price":173},{"name":"Islam Makhachev","price":-203}]}]},{"key":"betonlineag","title":"BetOnline.ag","last_update":"2022-10-21T23:52:00Z","markets":[{"key":"h2h","last_update":"2022-10-21T23:51:59Z","outcomes":[{"name":"Charles Oliveira","price":173},{"name":"Islam Makhachev","price":-204}]}]},{"key":"draftkings","title":"DraftKings","last_update":"2022-10-21T23:51:10Z","markets":[{"key":"h2h","last_update":"2022-10-21T23:51:10Z","outcomes":[{"name":"Charles Oliveira","price":160},{"name":"Islam Makhachev","price":-190}]}]},{"key":"williamhill_us","title":"William Hill (US)","last_update":"2022-10-21T23:52:52Z","markets":[{"key":"h2h","last_update":"2022-10-21T23:52:52Z","outcomes":[{"name":"Charles Oliveira","price":160},{"name":"Islam Makhachev","price":-190}]}]},{"key":"twinspires","title":"TwinSpires","last_update":"2022-10-21T23:54:23Z","markets":[{"key":"h2h","last_update":"2022-10-21T23:54:23Z","outcomes":[{"name":"Charles Oliveira","price":143},{"name":"Islam Makhachev","price":-177}]}]},{"key":"sugarhouse","title":"SugarHouse","last_update":"2022-10-21T23:53:38Z","markets":[{"key":"h2h","last_update":"2022-10-21T23:53:38Z","outcomes":[{"name":"Charles Oliveira","price":143},{"name":"Islam Makhachev","price":-177}]}]},{"key":"barstool","title":"Barstool Sportsbook","last_update":"2022-10-21T23:54:23Z","markets":[{"key":"h2h","last_update":"2022-10-21T23:54:23Z","outcomes":[{"name":"Charles Oliveira","price":143},{"name":"Islam Makhachev","price":-177}]}]},{"key":"betrivers","title":"BetRivers","last_update":"2022-10-21T23:54:25Z","markets":[{"key":"h2h","last_update":"2022-10-21T23:54:25Z","outcomes":[{"name":"Charles Oliveira","price":143},{"name":"Islam Makhachev","price":-177}]}]},{"key":"betfair","title":"Betfair","last_update":"2022-10-21T23:52:00Z","markets":[{"key":"h2h","last_update":"2022-10-21T23:52:00Z","outcomes":[{"name":"Charles Oliveira","price":168},{"name":"Islam Makhachev","price":-169}]},{"key":"h2h_lay","last_update":"2022-10-21T23:52:00Z","outcomes":[{"name":"Charles Oliveira","price":170},{"name":"Islam Makhachev","price":-167}]}]},{"key":"betmgm","title":"BetMGM","last_update":"2022-10-21T23:54:22Z","markets":[{"key":"h2h","last_update":"2022-10-21T23:54:22Z","outcomes":[{"name":"Charles Oliveira","price":145},{"name":"Islam Makhachev","price":-175}]}]},{"key":"mybookieag","title":"MyBookie.ag","last_update":"2022-10-21T23:48:51Z","markets":[{"key":"h2h","last_update":"2022-10-21T23:48:51Z","outcomes":[{"name":"Charles Oliveira","price":136},{"name":"Islam Makhachev","price":-175}]}]},{"key":"wynnbet","title":"WynnBET","last_update":"2022-10-21T23:53:38Z","markets":[{"key":"h2h","last_update":"2022-10-21T23:53:38Z","outcomes":[{"name":"Charles Oliveira","price":160},{"name":"Islam Makhachev","price":-196}]}]},{"key":"superbook","title":"SuperBook","last_update":"2022-10-21T23:54:23Z","markets":[{"key":"h2h","last_update":"2022-10-21T23:54:23Z","outcomes":[{"name":"Charles Oliveira","price":170},{"name":"Islam Makhachev","price":-190}]}]},{"key":"bovada","title":"Bovada","last_update":"2022-10-21T23:55:16Z","markets":[{"key":"h2h","last_update":"2022-10-21T23:55:16Z","outcomes":[{"name":"Charles Oliveira","price":150},{"name":"Islam Makhachev","price":-185}]}]},{"key":"unibet_us","title":"Unibet","last_update":"2022-10-21T23:53:39Z","markets":[{"key":"h2h","last_update":"2022-10-21T23:53:39Z","outcomes":[{"name":"Charles Oliveira","price":143},{"name":"Islam Makhachev","price":-177}]}]}]},{"id":"ce9d2be04a8130e804b060cff8cd9c81","sport_key":"mma_mixed_martial_arts","sport_title":"MMA","commence_time":"2022-10-23T03:20:00Z","home_team":"Aj Dobson","away_team":"Armen Petrosyan","bookmakers":[]},{"id":"8a632565a98c65d2ac7495cbbce345e1","sport_key":"mma_mixed_martial_arts","sport_title":"MMA","commence_time":"2022-10-29T23:00:00Z","home_team":"Andrei Arlovski","away_team":"Marcos Rogerio de Lima","bookmakers":[{"key":"lowvig","title":"LowVig.ag","last_update":"2022-10-21T23:53:47Z","markets":[{"key":"h2h","last_update":"2022-10-21T23:53:47Z","outcomes":[{"name":"Andrei Arlovski","price":165},{"name":"Marcos Rogerio de Lima","price":-190}]}]},{"key":"betonlineag","title":"BetOnline.ag","last_update":"2022-10-21T23:52:00Z","markets":[{"key":"h2h","last_update":"2022-10-21T23:52:00Z","outcomes":[{"name":"Andrei Arlovski","price":165},{"name":"Marcos Rogerio de Lima","price":-192}]}]},{"key":"draftkings","title":"DraftKings","last_update":"2022-10-21T23:51:10Z","markets":[{"key":"h2h","last_update":"2022-10-21T23:51:10Z","outcomes":[{"name":"Andrei Arlovski","price":155},{"name":"Marcos Rogerio de Lima","price":-180}]}]},{"key":"williamhill_us","title":"William Hill (US)","last_update":"2022-10-21T23:52:52Z","markets":[{"key":"h2h","last_update":"2022-10-21T23:52:52Z","outcomes":[{"name":"Andrei Arlovski","price":150},{"name":"Marcos Rogerio de Lima","price":-175}]}]},{"key":"betmgm","title":"BetMGM","last_update":"2022-10-21T23:54:22Z","markets":[{"key":"h2h","last_update":"2022-10-21T23:54:22Z","outcomes":[{"name":"Andrei Arlovski","price":145},{"name":"Marcos Rogerio de Lima","price":-175}]}]},{"key":"barstool","title":"Barstool Sportsbook","last_update":"2022-10-21T23:54:23Z","markets":[{"key":"h2h","last_update":"2022-10-21T23:54:23Z","outcomes":[{"name":"Andrei Arlovski","price":143},{"name":"Marcos Rogerio de Lima","price":-180}]}]},{"key":"twinspires","title":"TwinSpires","last_update":"2022-10-21T23:54:23Z","markets":[{"key":"h2h","last_update":"2022-10-21T23:54:23Z","outcomes":[{"name":"Andrei Arlovski","price":143},{"name":"Marcos Rogerio de Lima","price":-180}]}]},{"key":"sugarhouse","title":"SugarHouse","last_update":"2022-10-21T23:53:38Z","markets":[{"key":"h2h","last_update":"2022-10-21T23:53:38Z","outcomes":[{"name":"Andrei Arlovski","price":143},{"name":"Marcos Rogerio de Lima","price":-180}]}]},{"key":"betrivers","title":"BetRivers","last_update":"2022-10-21T23:54:25Z","markets":[{"key":"h2h","last_update":"2022-10-21T23:54:25Z","outcomes":[{"name":"Andrei Arlovski","price":143},{"name":"Marcos Rogerio de Lima","price":-180}]}]},{"key":"unibet_us","title":"Unibet","last_update":"2022-10-21T23:53:39Z","markets":[{"key":"h2h","last_update":"2022-10-21T23:53:39Z","outcomes":[{"name":"Andrei Arlovski","price":143},{"name":"Marcos Rogerio de Lima","price":-180}]}]},{"key":"fanduel","title":"FanDuel","last_update":"2022-10-21T23:51:11Z","markets":[{"key":"h2h","last_update":"2022-10-21T23:51:11Z","outcomes":[{"name":"Andrei Arlovski","price":146},{"name":"Marcos Rogerio de Lima","price":-174}]}]},{"key":"mybookieag","title":"MyBookie.ag","last_update":"2022-10-21T23:48:51Z","markets":[{"key":"h2h","last_update":"2022-10-21T23:48:51Z","outcomes":[{"name":"Andrei Arlovski","price":145},{"name":"Marcos Rogerio de Lima","price":-188}]}]},{"key":"superbook","title":"SuperBook","last_update":"2022-10-21T23:54:23Z","markets":[{"key":"h2h","last_update":"2022-10-21T23:54:23Z","outcomes":[{"name":"Andrei Arlovski","price":155},{"name":"Marcos Rogerio de Lima","price":-175}]}]}]},{"id":"ab23077cecc80d893fbe0be927deb4c4","sport_key":"mma_mixed_martial_arts","sport_title":"MMA","commence_time":"2022-10-29T23:00:00Z","home_team":"Calvin Kattar","away_team":"Arnold Allen","bookmakers":[{"key":"fanduel","title":"FanDuel","last_update":"2022-10-21T23:51:11Z","markets":[{"key":"h2h","last_update":"2022-10-21T23:51:11Z","outcomes":[{"name":"Arnold Allen","price":110},{"name":"Calvin Kattar","price":-130}]}]},{"key":"betonlineag","title":"BetOnline.ag","last_update":"2022-10-21T23:52:00Z","markets":[{"key":"h2h","last_update":"2022-10-21T23:52:00Z","outcomes":[{"name":"Arnold Allen","price":111},{"name":"Calvin Kattar","price":-132}]}]},{"key":"lowvig","title":"LowVig.ag","last_update":"2022-10-21T23:53:47Z","markets":[{"key":"h2h","last_update":"2022-10-21T23:53:47Z","outcomes":[{"name":"Arnold Allen","price":111},{"name":"Calvin Kattar","price":-131}]}]},{"key":"draftkings","title":"DraftKings","last_update":"2022-10-21T23:51:10Z","markets":[{"key":"h2h","last_update":"2022-10-21T23:51:10Z","outcomes":[{"name":"Arnold Allen","price":110},{"name":"Calvin Kattar","price":-130}]}]},{"key":"betrivers","title":"BetRivers","last_update":"2022-10-21T23:54:25Z","markets":[{"key":"h2h","last_update":"2022-10-21T23:54:25Z","outcomes":[{"name":"Arnold Allen","price":102},{"name":"Calvin Kattar","price":-125}]}]},{"key":"twinspires","title":"TwinSpires","last_update":"2022-10-21T23:54:23Z","markets":[{"key":"h2h","last_update":"2022-10-21T23:54:23Z","outcomes":[{"name":"Arnold Allen","price":102},{"name":"Calvin Kattar","price":-125}]}]},{"key":"sugarhouse","title":"SugarHouse","last_update":"2022-10-21T23:53:38Z","markets":[{"key":"h2h","last_update":"2022-10-21T23:53:38Z","outcomes":[{"name":"Arnold Allen","price":102},{"name":"Calvin Kattar","price":-125}]}]},{"key":"barstool","title":"Barstool Sportsbook","last_update":"2022-10-21T23:54:23Z","markets":[{"key":"h2h","last_update":"2022-10-21T23:54:23Z","outcomes":[{"name":"Arnold Allen","price":102},{"name":"Calvin Kattar","price":-125}]}]},{"key":"williamhill_us","title":"William Hill (US)","last_update":"2022-10-21T23:52:52Z","markets":[{"key":"h2h","last_update":"2022-10-21T23:52:52Z","outcomes":[{"name":"Arnold Allen","price":105},{"name":"Calvin Kattar","price":-125}]}]},{"key":"betmgm","title":"BetMGM","last_update":"2022-10-21T23:54:22Z","markets":[{"key":"h2h","last_update":"2022-10-21T23:54:22Z","outcomes":[{"name":"Arnold Allen","price":105},{"name":"Calvin Kattar","price":-130}]}]},{"key":"unibet_us","title":"Unibet","last_update":"2022-10-21T23:53:39Z","markets":[{"key":"h2h","last_update":"2022-10-21T23:53:39Z","outcomes":[{"name":"Arnold Allen","price":102},{"name":"Calvin Kattar","price":-125}]}]}]},{"id":"b06c4d895a667e053dc6975ca1e0e0f5","sport_key":"mma_mixed_martial_arts","sport_title":"MMA","commence_time":"2022-10-29T23:00:00Z","home_team":"Chase Hooper","away_team":"Steve Garcia Jr.","bookmakers":[{"key":"lowvig","title":"LowVig.ag","last_update":"2022-10-21T23:53:47Z","markets":[{"key":"h2h","last_update":"2022-10-21T23:53:47Z","outcomes":[{"name":"Chase Hooper","price":-211},{"name":"Steve Garcia Jr.","price":181}]}]},{"key":"betonlineag","title":"BetOnline.ag","last_update":"2022-10-21T23:52:00Z","markets":[{"key":"h2h","last_update":"2022-10-21T23:52:00Z","outcomes":[{"name":"Chase Hooper","price":-213},{"name":"Steve Garcia Jr.","price":181}]}]},{"key":"draftkings","title":"DraftKings","last_update":"2022-10-21T23:51:10Z","markets":[{"key":"h2h","last_update":"2022-10-21T23:51:10Z","outcomes":[{"name":"Chase Hooper","price":-210},{"name":"Steve Garcia Jr.","price":180}]}]},{"key":"williamhill_us","title":"William Hill (US)","last_update":"2022-10-21T23:52:52Z","markets":[{"key":"h2h","last_update":"2022-10-21T23:52:52Z","outcomes":[{"name":"Chase Hooper","price":-220},{"name":"Steve Garcia Jr.","price":180}]}]},{"key":"betmgm","title":"BetMGM","last_update":"2022-10-21T23:54:22Z","markets":[{"key":"h2h","last_update":"2022-10-21T23:54:22Z","outcomes":[{"name":"Chase Hooper","price":-225},{"name":"Steve Garcia Jr.","price":180}]}]},{"key":"barstool","title":"Barstool Sportsbook","last_update":"2022-10-21T23:54:23Z","markets":[{"key":"h2h","last_update":"2022-10-21T23:54:23Z","outcomes":[{"name":"Chase Hooper","price":-230},{"name":"Steve Garcia Jr.","price":180}]}]},{"key":"twinspires","title":"TwinSpires","last_update":"2022-10-21T23:54:23Z","markets":[{"key":"h2h","last_update":"2022-10-21T23:54:23Z","outcomes":[{"name":"Chase Hooper","price":-230},{"name":"Steve Garcia Jr.","price":180}]}]},{"key":"sugarhouse","title":"SugarHouse","last_update":"2022-10-21T23:53:38Z","markets":[{"key":"h2h","last_update":"2022-10-21T23:53:38Z","outcomes":[{"name":"Chase Hooper","price":-230},{"name":"Steve Garcia Jr.","price":180}]}]},{"key":"betrivers","title":"BetRivers","last_update":"2022-10-21T23:54:25Z","markets":[{"key":"h2h","last_update":"2022-10-21T23:54:25Z","outcomes":[{"name":"Chase Hooper","price":-230},{"name":"Steve Garcia Jr.","price":180}]}]},{"key":"unibet_us","title":"Unibet","last_update":"2022-10-21T23:53:39Z","markets":[{"key":"h2h","last_update":"2022-10-21T23:53:39Z","outcomes":[{"name":"Chase Hooper","price":-230},{"name":"Steve Garcia Jr.","price":180}]}]},{"key":"fanduel","title":"FanDuel","last_update":"2022-10-21T23:51:11Z","markets":[{"key":"h2h","last_update":"2022-10-21T23:51:11Z","outcomes":[{"name":"Chase Hooper","price":-210},{"name":"Steve Garcia Jr.","price":176}]}]},{"key":"mybookieag","title":"MyBookie.ag","last_update":"2022-10-21T23:48:51Z","markets":[{"key":"h2h","last_update":"2022-10-21T23:48:51Z","outcomes":[{"name":"Chase Hooper","price":-222},{"name":"Steve Garcia Jr.","price":171}]}]},{"key":"superbook","title":"SuperBook","last_update":"2022-10-21T23:54:23Z","markets":[{"key":"h2h","last_update":"2022-10-21T23:54:23Z","outcomes":[{"name":"Chase Hooper","price":-210},{"name":"Steve Garcia Jr.","price":180}]}]}]},{"id":"f14ecf19ff5792ebb28045d8ee4dd7fb","sport_key":"mma_mixed_martial_arts","sport_title":"MMA","commence_time":"2022-10-29T23:00:00Z","home_team":"Christian Rodriguez","away_team":"Garrett Armfield","bookmakers":[{"key":"lowvig","title":"LowVig.ag","last_update":"2022-10-21T23:53:47Z","markets":[{"key":"h2h","last_update":"2022-10-21T23:53:47Z","outcomes":[{"name":"Christian Rodriguez","price":-210},{"name":"Garrett Armfield","price":180}]}]},{"key":"betonlineag","title":"BetOnline.ag","last_update":"2022-10-21T23:52:00Z","markets":[{"key":"h2h","last_update":"2022-10-21T23:52:00Z","outcomes":[{"name":"Christian Rodriguez","price":-213},{"name":"Garrett Armfield","price":180}]}]},{"key":"draftkings","title":"DraftKings","last_update":"2022-10-21T23:51:10Z","markets":[{"key":"h2h","last_update":"2022-10-21T23:51:10Z","outcomes":[{"name":"Christian Rodriguez","price":-205},{"name":"Garrett Armfield","price":175}]}]},{"key":"williamhill_us","title":"William Hill (US)","last_update":"2022-10-21T23:52:52Z","markets":[{"key":"h2h","last_update":"2022-10-21T23:52:52Z","outcomes":[{"name":"Christian Rodriguez","price":-210},{"name":"Garrett Armfield","price":175}]}]},{"key":"betmgm","title":"BetMGM","last_update":"2022-10-21T23:54:22Z","markets":[{"key":"h2h","last_update":"2022-10-21T23:54:22Z","outcomes":[{"name":"Christian Rodriguez","price":-210},{"name":"Garrett Armfield","price":165}]}]},{"key":"barstool","title":"Barstool Sportsbook","last_update":"2022-10-21T23:54:23Z","markets":[{"key":"h2h","last_update":"2022-10-21T23:54:23Z","outcomes":[{"name":"Christian Rodriguez","price":-205},{"name":"Garrett Armfield","price":163}]}]},{"key":"twinspires","title":"TwinSpires","last_update":"2022-10-21T23:54:23Z","markets":[{"key":"h2h","last_update":"2022-10-21T23:54:23Z","outcomes":[{"name":"Christian Rodriguez","price":-205},{"name":"Garrett Armfield","price":163}]}]},{"key":"sugarhouse","title":"SugarHouse","last_update":"2022-10-21T23:53:38Z","markets":[{"key":"h2h","last_update":"2022-10-21T23:53:38Z","outcomes":[{"name":"Christian Rodriguez","price":-205},{"name":"Garrett Armfield","price":163}]}]},{"key":"betrivers","title":"BetRivers","last_update":"2022-10-21T23:54:25Z","markets":[{"key":"h2h","last_update":"2022-10-21T23:54:25Z","outcomes":[{"name":"Christian Rodriguez","price":-205},{"name":"Garrett Armfield","price":163}]}]},{"key":"unibet_us","title":"Unibet","last_update":"2022-10-21T23:53:39Z","markets":[{"key":"h2h","last_update":"2022-10-21T23:53:39Z","outcomes":[{"name":"Christian Rodriguez","price":-205},{"name":"Garrett Armfield","price":163}]}]},{"key":"fanduel","title":"FanDuel","last_update":"2022-10-21T23:51:11Z","markets":[{"key":"h2h","last_update":"2022-10-21T23:51:11Z","outcomes":[{"name":"Christian Rodriguez","price":-200},{"name":"Garrett Armfield","price":168}]}]},{"key":"mybookieag","title":"MyBookie.ag","last_update":"2022-10-21T23:48:51Z","markets":[{"key":"h2h","last_update":"2022-10-21T23:48:51Z","outcomes":[{"name":"Christian Rodriguez","price":-217},{"name":"Garrett Armfield","price":166}]}]},{"key":"superbook","title":"SuperBook","last_update":"2022-10-21T23:54:23Z","markets":[{"key":"h2h","last_update":"2022-10-21T23:54:23Z","outcomes":[{"name":"Christian Rodriguez","price":-200},{"name":"Garrett Armfield","price":175}]}]}]},{"id":"57e7c6a8d4975cd1cd1c36eb71de4281","sport_key":"mma_mixed_martial_arts","sport_title":"MMA","commence_time":"2022-10-29T23:00:00Z","home_team":"Cody Durden","away_team":"Kleydson Rodrigues","bookmakers":[{"key":"lowvig","title":"LowVig.ag","last_update":"2022-10-21T23:53:47Z","markets":[{"key":"h2h","last_update":"2022-10-21T23:53:47Z","outcomes":[{"name":"Cody Durden","price":145},{"name":"Kleydson Rodrigues","price":-170}]}]},{"key":"betonlineag","title":"BetOnline.ag","last_update":"2022-10-21T23:52:00Z","markets":[{"key":"h2h","last_update":"2022-10-21T23:52:00Z","outcomes":[{"name":"Cody Durden","price":145},{"name":"Kleydson Rodrigues","price":-172}]}]},{"key":"draftkings","title":"DraftKings","last_update":"2022-10-21T23:51:10Z","markets":[{"key":"h2h","last_update":"2022-10-21T23:51:10Z","outcomes":[{"name":"Cody Durden","price":150},{"name":"Kleydson Rodrigues","price":-175}]}]},{"key":"williamhill_us","title":"William Hill (US)","last_update":"2022-10-21T23:52:52Z","markets":[{"key":"h2h","last_update":"2022-10-21T23:52:52Z","outcomes":[{"name":"Cody Durden","price":150},{"name":"Kleydson Rodrigues","price":-175}]}]},{"key":"betmgm","title":"BetMGM","last_update":"2022-10-21T23:54:22Z","markets":[{"key":"h2h","last_update":"2022-10-21T23:54:22Z","outcomes":[{"name":"Cody Durden","price":145},{"name":"Kleydson Rodrigues","price":-175}]}]},{"key":"barstool","title":"Barstool Sportsbook","last_update":"2022-10-21T23:54:23Z","markets":[{"key":"h2h","last_update":"2022-10-21T23:54:23Z","outcomes":[{"name":"Cody Durden","price":138},{"name":"Kleydson Rodrigues","price":-175}]}]},{"key":"twinspires","title":"TwinSpires","last_update":"2022-10-21T23:54:23Z","markets":[{"key":"h2h","last_update":"2022-10-21T23:54:23Z","outcomes":[{"name":"Cody Durden","price":138},{"name":"Kleydson Rodrigues","price":-175}]}]},{"key":"sugarhouse","title":"SugarHouse","last_update":"2022-10-21T23:53:38Z","markets":[{"key":"h2h","last_update":"2022-10-21T23:53:38Z","outcomes":[{"name":"Cody Durden","price":138},{"name":"Kleydson Rodrigues","price":-175}]}]},{"key":"betrivers","title":"BetRivers","last_update":"2022-10-21T23:54:25Z","markets":[{"key":"h2h","last_update":"2022-10-21T23:54:25Z","outcomes":[{"name":"Cody Durden","price":138},{"name":"Kleydson Rodrigues","price":-175}]}]},{"key":"unibet_us","title":"Unibet","last_update":"2022-10-21T23:53:39Z","markets":[{"key":"h2h","last_update":"2022-10-21T23:53:39Z","outcomes":[{"name":"Cody Durden","price":138},{"name":"Kleydson Rodrigues","price":-175}]}]},{"key":"fanduel","title":"FanDuel","last_update":"2022-10-21T23:51:11Z","markets":[{"key":"h2h","last_update":"2022-10-21T23:51:11Z","outcomes":[{"name":"Cody Durden","price":142},{"name":"Kleydson Rodrigues","price":-168}]}]},{"key":"mybookieag","title":"MyBookie.ag","last_update":"2022-10-21T23:48:51Z","markets":[{"key":"h2h","last_update":"2022-10-21T23:48:51Z","outcomes":[{"name":"Cody Durden","price":142},{"name":"Kleydson Rodrigues","price":-181}]}]},{"key":"superbook","title":"SuperBook","last_update":"2022-10-21T23:54:23Z","markets":[{"key":"h2h","last_update":"2022-10-21T23:54:23Z","outcomes":[{"name":"Cody Durden","price":150},{"name":"Kleydson Rodrigues","price":-170}]}]}]},{"id":"619772363e6384131e1c8cc09849a4c7","sport_key":"mma_mixed_martial_arts","sport_title":"MMA","commence_time":"2022-10-29T23:00:00Z","home_team":"Dustin Jacoby","away_team":"Khalil Rountree","bookmakers":[{"key":"lowvig","title":"LowVig.ag","last_update":"2022-10-21T23:53:47Z","markets":[{"key":"h2h","last_update":"2022-10-21T23:53:47Z","outcomes":[{"name":"Dustin Jacoby","price":-155},{"name":"Khalil Rountree","price":135}]}]},{"key":"betonlineag","title":"BetOnline.ag","last_update":"2022-10-21T23:52:00Z","markets":[{"key":"h2h","last_update":"2022-10-21T23:52:00Z","outcomes":[{"name":"Dustin Jacoby","price":-156},{"name":"Khalil Rountree","price":135}]}]},{"key":"draftkings","title":"DraftKings","last_update":"2022-10-21T23:51:10Z","markets":[{"key":"h2h","last_update":"2022-10-21T23:51:10Z","outcomes":[{"name":"Dustin Jacoby","price":-165},{"name":"Khalil Rountree","price":140}]}]},{"key":"williamhill_us","title":"William Hill (US)","last_update":"2022-10-21T23:52:52Z","markets":[{"key":"h2h","last_update":"2022-10-21T23:52:52Z","outcomes":[{"name":"Dustin Jacoby","price":-170},{"name":"Khalil Rountree","price":145}]}]},{"key":"betmgm","title":"BetMGM","last_update":"2022-10-21T23:54:22Z","markets":[{"key":"h2h","last_update":"2022-10-21T23:54:22Z","outcomes":[{"name":"Dustin Jacoby","price":-185},{"name":"Khalil Rountree","price":150}]}]},{"key":"barstool","title":"Barstool Sportsbook","last_update":"2022-10-21T23:54:23Z","markets":[{"key":"h2h","last_update":"2022-10-21T23:54:23Z","outcomes":[{"name":"Dustin Jacoby","price":-175},{"name":"Khalil Rountree","price":138}]}]},{"key":"twinspires","title":"TwinSpires","last_update":"2022-10-21T23:54:23Z","markets":[{"key":"h2h","last_update":"2022-10-21T23:54:23Z","outcomes":[{"name":"Dustin Jacoby","price":-175},{"name":"Khalil Rountree","price":138}]}]},{"key":"sugarhouse","title":"SugarHouse","last_update":"2022-10-21T23:53:38Z","markets":[{"key":"h2h","last_update":"2022-10-21T23:53:38Z","outcomes":[{"name":"Dustin Jacoby","price":-175},{"name":"Khalil Rountree","price":138}]}]},{"key":"betrivers","title":"BetRivers","last_update":"2022-10-21T23:54:25Z","markets":[{"key":"h2h","last_update":"2022-10-21T23:54:25Z","outcomes":[{"name":"Dustin Jacoby","price":-175},{"name":"Khalil Rountree","price":138}]}]},{"key":"unibet_us","title":"Unibet","last_update":"2022-10-21T23:53:39Z","markets":[{"key":"h2h","last_update":"2022-10-21T23:53:39Z","outcomes":[{"name":"Dustin Jacoby","price":-175},{"name":"Khalil Rountree","price":138}]}]},{"key":"fanduel","title":"FanDuel","last_update":"2022-10-21T23:51:11Z","markets":[{"key":"h2h","last_update":"2022-10-21T23:51:11Z","outcomes":[{"name":"Dustin Jacoby","price":-168},{"name":"Khalil Rountree","price":142}]}]},{"key":"mybookieag","title":"MyBookie.ag","last_update":"2022-10-21T23:48:51Z","markets":[{"key":"h2h","last_update":"2022-10-21T23:48:51Z","outcomes":[{"name":"Dustin Jacoby","price":-178},{"name":"Khalil Rountree","price":139}]}]},{"key":"superbook","title":"SuperBook","last_update":"2022-10-21T23:54:23Z","markets":[{"key":"h2h","last_update":"2022-10-21T23:54:23Z","outcomes":[{"name":"Dustin Jacoby","price":-170},{"name":"Khalil Rountree","price":150}]}]}]},{"id":"81c55a1f7758c1513d3604afa61b06f2","sport_key":"mma_mixed_martial_arts","sport_title":"MMA","commence_time":"2022-10-29T23:00:00Z","home_team":"Waldo Cortes-Acosta","away_team":"Jared Vanderaa","bookmakers":[{"key":"lowvig","title":"LowVig.ag","last_update":"2022-10-21T23:53:47Z","markets":[{"key":"h2h","last_update":"2022-10-21T23:53:47Z","outcomes":[{"name":"Jared Vanderaa","price":168},{"name":"Waldo Cortes-Acosta","price":-193}]}]},{"key":"betonlineag","title":"BetOnline.ag","last_update":"2022-10-21T23:52:00Z","markets":[{"key":"h2h","last_update":"2022-10-21T23:52:00Z","outcomes":[{"name":"Jared Vanderaa","price":168},{"name":"Waldo Cortes-Acosta","price":-196}]}]},{"key":"draftkings","title":"DraftKings","last_update":"2022-10-21T23:51:10Z","markets":[{"key":"h2h","last_update":"2022-10-21T23:51:10Z","outcomes":[{"name":"Jared Vanderaa","price":165},{"name":"Waldo Cortes-Acosta","price":-195}]}]},{"key":"williamhill_us","title":"William Hill (US)","last_update":"2022-10-21T23:52:52Z","markets":[{"key":"h2h","last_update":"2022-10-21T23:52:52Z","outcomes":[{"name":"Jared Vanderaa","price":165},{"name":"Waldo Cortes-Acosta","price":-195}]}]},{"key":"betmgm","title":"BetMGM","last_update":"2022-10-21T23:54:22Z","markets":[{"key":"h2h","last_update":"2022-10-21T23:54:22Z","outcomes":[{"name":"Jared Vanderaa","price":165},{"name":"Waldo Cortes-Acosta","price":-210}]}]},{"key":"barstool","title":"Barstool Sportsbook","last_update":"2022-10-21T23:54:23Z","markets":[{"key":"h2h","last_update":"2022-10-21T23:54:23Z","outcomes":[{"name":"Jared Vanderaa","price":163},{"name":"Waldo Cortes-Acosta","price":-205}]}]},{"key":"twinspires","title":"TwinSpires","last_update":"2022-10-21T23:54:23Z","markets":[{"key":"h2h","last_update":"2022-10-21T23:54:23Z","outcomes":[{"name":"Jared Vanderaa","price":163},{"name":"Waldo Cortes-Acosta","price":-205}]}]},{"key":"sugarhouse","title":"SugarHouse","last_update":"2022-10-21T23:53:38Z","markets":[{"key":"h2h","last_update":"2022-10-21T23:53:38Z","outcomes":[{"name":"Jared Vanderaa","price":163},{"name":"Waldo Cortes-Acosta","price":-205}]}]},{"key":"betrivers","title":"BetRivers","last_update":"2022-10-21T23:54:25Z","markets":[{"key":"h2h","last_update":"2022-10-21T23:54:25Z","outcomes":[{"name":"Jared Vanderaa","price":163},{"name":"Waldo Cortes-Acosta","price":-205}]}]},{"key":"unibet_us","title":"Unibet","last_update":"2022-10-21T23:53:39Z","markets":[{"key":"h2h","last_update":"2022-10-21T23:53:39Z","outcomes":[{"name":"Jared Vanderaa","price":163},{"name":"Waldo Cortes-Acosta","price":-205}]}]},{"key":"fanduel","title":"FanDuel","last_update":"2022-10-21T23:51:11Z","markets":[{"key":"h2h","last_update":"2022-10-21T23:51:11Z","outcomes":[{"name":"Jared Vanderaa","price":168},{"name":"Waldo Cortes-Acosta","price":-200}]}]},{"key":"mybookieag","title":"MyBookie.ag","last_update":"2022-10-21T23:48:51Z","markets":[{"key":"h2h","last_update":"2022-10-21T23:48:51Z","outcomes":[{"name":"Jared Vanderaa","price":157},{"name":"Waldo Cortes-Acosta","price":-204}]}]},{"key":"superbook","title":"SuperBook","last_update":"2022-10-21T23:54:23Z","markets":[{"key":"h2h","last_update":"2022-10-21T23:54:23Z","outcomes":[{"name":"Jared Vanderaa","price":170},{"name":"Waldo Cortes-Acosta","price":-190}]}]}]},{"id":"44e464accfadf65923d7ef98dfbfd6a3","sport_key":"mma_mixed_martial_arts","sport_title":"MMA","commence_time":"2022-10-29T23:00:00Z","home_team":"Joseph Holmes","away_team":"Jun Yong Park","bookmakers":[{"key":"lowvig","title":"LowVig.ag","last_update":"2022-10-21T23:53:47Z","markets":[{"key":"h2h","last_update":"2022-10-21T23:53:47Z","outcomes":[{"name":"Joseph Holmes","price":200},{"name":"Jun Yong Park","price":-235}]}]},{"key":"betonlineag","title":"BetOnline.ag","last_update":"2022-10-21T23:52:00Z","markets":[{"key":"h2h","last_update":"2022-10-21T23:52:00Z","outcomes":[{"name":"Joseph Holmes","price":200},{"name":"Jun Yong Park","price":-238}]}]},{"key":"draftkings","title":"DraftKings","last_update":"2022-10-21T23:51:10Z","markets":[{"key":"h2h","last_update":"2022-10-21T23:51:10Z","outcomes":[{"name":"Joseph Holmes","price":200},{"name":"Jun Yong Park","price":-240}]}]},{"key":"williamhill_us","title":"William Hill (US)","last_update":"2022-10-21T23:52:52Z","markets":[{"key":"h2h","last_update":"2022-10-21T23:52:52Z","outcomes":[{"name":"Joseph Holmes","price":190},{"name":"Jun Yong Park","price":-230}]}]},{"key":"betmgm","title":"BetMGM","last_update":"2022-10-21T23:54:22Z","markets":[{"key":"h2h","last_update":"2022-10-21T23:54:22Z","outcomes":[{"name":"Joseph Holmes","price":190},{"name":"Jun Yong Park","price":-250}]}]},{"key":"barstool","title":"Barstool Sportsbook","last_update":"2022-10-21T23:54:23Z","markets":[{"key":"h2h","last_update":"2022-10-21T23:54:23Z","outcomes":[{"name":"Joseph Holmes","price":195},{"name":"Jun Yong Park","price":-250}]}]},{"key":"twinspires","title":"TwinSpires","last_update":"2022-10-21T23:54:23Z","markets":[{"key":"h2h","last_update":"2022-10-21T23:54:23Z","outcomes":[{"name":"Joseph Holmes","price":195},{"name":"Jun Yong Park","price":-250}]}]},{"key":"sugarhouse","title":"SugarHouse","last_update":"2022-10-21T23:53:38Z","markets":[{"key":"h2h","last_update":"2022-10-21T23:53:38Z","outcomes":[{"name":"Joseph Holmes","price":195},{"name":"Jun Yong Park","price":-250}]}]},{"key":"betrivers","title":"BetRivers","last_update":"2022-10-21T23:54:25Z","markets":[{"key":"h2h","last_update":"2022-10-21T23:54:25Z","outcomes":[{"name":"Joseph Holmes","price":195},{"name":"Jun Yong Park","price":-250}]}]},{"key":"unibet_us","title":"Unibet","last_update":"2022-10-21T23:53:39Z","markets":[{"key":"h2h","last_update":"2022-10-21T23:53:39Z","outcomes":[{"name":"Joseph Holmes","price":195},{"name":"Jun Yong Park","price":-250}]}]},{"key":"fanduel","title":"FanDuel","last_update":"2022-10-21T23:51:11Z","markets":[{"key":"h2h","last_update":"2022-10-21T23:51:11Z","outcomes":[{"name":"Joseph Holmes","price":188},{"name":"Jun Yong Park","price":-225}]}]},{"key":"mybookieag","title":"MyBookie.ag","last_update":"2022-10-21T23:48:51Z","markets":[{"key":"h2h","last_update":"2022-10-21T23:48:51Z","outcomes":[{"name":"Joseph Holmes","price":190},{"name":"Jun Yong Park","price":-250}]}]}]},{"id":"114c001dd993caac0826766b38253d74","sport_key":"mma_mixed_martial_arts","sport_title":"MMA","commence_time":"2022-10-29T23:00:00Z","home_team":"Tresean Gore","away_team":"Josh Fremd","bookmakers":[{"key":"lowvig","title":"LowVig.ag","last_update":"2022-10-21T23:53:47Z","markets":[{"key":"h2h","last_update":"2022-10-21T23:53:47Z","outcomes":[{"name":"Josh Fremd","price":-190},{"name":"Tresean Gore","price":165}]}]},{"key":"betonlineag","title":"BetOnline.ag","last_update":"2022-10-21T23:52:00Z","markets":[{"key":"h2h","last_update":"2022-10-21T23:52:00Z","outcomes":[{"name":"Josh Fremd","price":-192},{"name":"Tresean Gore","price":165}]}]},{"key":"draftkings","title":"DraftKings","last_update":"2022-10-21T23:51:10Z","markets":[{"key":"h2h","last_update":"2022-10-21T23:51:10Z","outcomes":[{"name":"Josh Fremd","price":-190},{"name":"Tresean Gore","price":160}]}]},{"key":"williamhill_us","title":"William Hill (US)","last_update":"2022-10-21T23:52:52Z","markets":[{"key":"h2h","last_update":"2022-10-21T23:52:52Z","outcomes":[{"name":"Josh Fremd","price":-175},{"name":"Tresean Gore","price":150}]}]},{"key":"betmgm","title":"BetMGM","last_update":"2022-10-21T23:54:22Z","markets":[{"key":"h2h","last_update":"2022-10-21T23:54:22Z","outcomes":[{"name":"Josh Fremd","price":-175},{"name":"Tresean Gore","price":145}]}]},{"key":"barstool","title":"Barstool Sportsbook","last_update":"2022-10-21T23:54:23Z","markets":[{"key":"h2h","last_update":"2022-10-21T23:54:23Z","outcomes":[{"name":"Josh Fremd","price":-177},{"name":"Tresean Gore","price":140}]}]},{"key":"twinspires","title":"TwinSpires","last_update":"2022-10-21T23:54:23Z","markets":[{"key":"h2h","last_update":"2022-10-21T23:54:23Z","outcomes":[{"name":"Josh Fremd","price":-177},{"name":"Tresean Gore","price":140}]}]},{"key":"sugarhouse","title":"SugarHouse","last_update":"2022-10-21T23:53:38Z","markets":[{"key":"h2h","last_update":"2022-10-21T23:53:38Z","outcomes":[{"name":"Josh Fremd","price":-177},{"name":"Tresean Gore","price":140}]}]},{"key":"betrivers","title":"BetRivers","last_update":"2022-10-21T23:54:25Z","markets":[{"key":"h2h","last_update":"2022-10-21T23:54:25Z","outcomes":[{"name":"Josh Fremd","price":-177},{"name":"Tresean Gore","price":140}]}]},{"key":"unibet_us","title":"Unibet","last_update":"2022-10-21T23:53:39Z","markets":[{"key":"h2h","last_update":"2022-10-21T23:53:39Z","outcomes":[{"name":"Josh Fremd","price":-177},{"name":"Tresean Gore","price":140}]}]},{"key":"fanduel","title":"FanDuel","last_update":"2022-10-21T23:51:11Z","markets":[{"key":"h2h","last_update":"2022-10-21T23:51:11Z","outcomes":[{"name":"Josh Fremd","price":-174},{"name":"Tresean Gore","price":146}]}]}]},{"id":"05836ab3d565d96b01df931a0be97b71","sport_key":"mma_mixed_martial_arts","sport_title":"MMA","commence_time":"2022-10-29T23:00:00Z","home_team":"Tim Means","away_team":"Max Griffin","bookmakers":[{"key":"lowvig","title":"LowVig.ag","last_update":"2022-10-21T23:53:47Z","markets":[{"key":"h2h","last_update":"2022-10-21T23:53:47Z","outcomes":[{"name":"Max Griffin","price":-186},{"name":"Tim Means","price":161}]}]},{"key":"betonlineag","title":"BetOnline.ag","last_update":"2022-10-21T23:52:00Z","markets":[{"key":"h2h","last_update":"2022-10-21T23:52:00Z","outcomes":[{"name":"Max Griffin","price":-189},{"name":"Tim Means","price":161}]}]},{"key":"draftkings","title":"DraftKings","last_update":"2022-10-21T23:51:10Z","markets":[{"key":"h2h","last_update":"2022-10-21T23:51:10Z","outcomes":[{"name":"Max Griffin","price":-190},{"name":"Tim Means","price":160}]}]},{"key":"williamhill_us","title":"William Hill (US)","last_update":"2022-10-21T23:52:52Z","markets":[{"key":"h2h","last_update":"2022-10-21T23:52:52Z","outcomes":[{"name":"Max Griffin","price":-180},{"name":"Tim Means","price":155}]}]},{"key":"betmgm","title":"BetMGM","last_update":"2022-10-21T23:54:22Z","markets":[{"key":"h2h","last_update":"2022-10-21T23:54:22Z","outcomes":[{"name":"Max Griffin","price":-185},{"name":"Tim Means","price":150}]}]},{"key":"barstool","title":"Barstool Sportsbook","last_update":"2022-10-21T23:54:23Z","markets":[{"key":"h2h","last_update":"2022-10-21T23:54:23Z","outcomes":[{"name":"Max Griffin","price":-182},{"name":"Tim Means","price":145}]}]},{"key":"twinspires","title":"TwinSpires","last_update":"2022-10-21T23:54:23Z","markets":[{"key":"h2h","last_update":"2022-10-21T23:54:23Z","outcomes":[{"name":"Max Griffin","price":-182},{"name":"Tim Means","price":145}]}]},{"key":"sugarhouse","title":"SugarHouse","last_update":"2022-10-21T23:53:38Z","markets":[{"key":"h2h","last_update":"2022-10-21T23:53:38Z","outcomes":[{"name":"Max Griffin","price":-182},{"name":"Tim Means","price":145}]}]},{"key":"betrivers","title":"BetRivers","last_update":"2022-10-21T23:54:25Z","markets":[{"key":"h2h","last_update":"2022-10-21T23:54:25Z","outcomes":[{"name":"Max Griffin","price":-182},{"name":"Tim Means","price":145}]}]},{"key":"unibet_us","title":"Unibet","last_update":"2022-10-21T23:53:39Z","markets":[{"key":"h2h","last_update":"2022-10-21T23:53:39Z","outcomes":[{"name":"Max Griffin","price":-182},{"name":"Tim Means","price":145}]}]},{"key":"fanduel","title":"FanDuel","last_update":"2022-10-21T23:51:11Z","markets":[{"key":"h2h","last_update":"2022-10-21T23:51:11Z","outcomes":[{"name":"Max Griffin","price":-184},{"name":"Tim Means","price":154}]}]},{"key":"mybookieag","title":"MyBookie.ag","last_update":"2022-10-21T23:48:51Z","markets":[{"key":"h2h","last_update":"2022-10-21T23:48:51Z","outcomes":[{"name":"Max Griffin","price":-188},{"name":"Tim Means","price":146}]}]}]},{"id":"e090052e8db2b4656d919060ad80761c","sport_key":"mma_mixed_martial_arts","sport_title":"MMA","commence_time":"2022-10-29T23:00:00Z","home_team":"Roman Dolidze","away_team":"Phil Hawes","bookmakers":[{"key":"lowvig","title":"LowVig.ag","last_update":"2022-10-21T23:53:47Z","markets":[{"key":"h2h","last_update":"2022-10-21T23:53:47Z","outcomes":[{"name":"Phil Hawes","price":-170},{"name":"Roman Dolidze","price":145}]}]},{"key":"betonlineag","title":"BetOnline.ag","last_update":"2022-10-21T23:52:00Z","markets":[{"key":"h2h","last_update":"2022-10-21T23:52:00Z","outcomes":[{"name":"Phil Hawes","price":-172},{"name":"Roman Dolidze","price":145}]}]},{"key":"draftkings","title":"DraftKings","last_update":"2022-10-21T23:51:10Z","markets":[{"key":"h2h","last_update":"2022-10-21T23:51:10Z","outcomes":[{"name":"Phil Hawes","price":-165},{"name":"Roman Dolidze","price":140}]}]},{"key":"williamhill_us","title":"William Hill (US)","last_update":"2022-10-21T23:52:52Z","markets":[{"key":"h2h","last_update":"2022-10-21T23:52:52Z","outcomes":[{"name":"Phil Hawes","price":-160},{"name":"Roman Dolidze","price":135}]}]},{"key":"betmgm","title":"BetMGM","last_update":"2022-10-21T23:54:22Z","markets":[{"key":"h2h","last_update":"2022-10-21T23:54:22Z","outcomes":[{"name":"Phil Hawes","price":-175},{"name":"Roman Dolidze","price":145}]}]},{"key":"barstool","title":"Barstool Sportsbook","last_update":"2022-10-21T23:54:23Z","markets":[{"key":"h2h","last_update":"2022-10-21T23:54:23Z","outcomes":[{"name":"Phil Hawes","price":-177},{"name":"Roman Dolidze","price":140}]}]},{"key":"twinspires","title":"TwinSpires","last_update":"2022-10-21T23:54:23Z","markets":[{"key":"h2h","last_update":"2022-10-21T23:54:23Z","outcomes":[{"name":"Phil Hawes","price":-177},{"name":"Roman Dolidze","price":140}]}]},{"key":"sugarhouse","title":"SugarHouse","last_update":"2022-10-21T23:53:38Z","markets":[{"key":"h2h","last_update":"2022-10-21T23:53:38Z","outcomes":[{"name":"Phil Hawes","price":-177},{"name":"Roman Dolidze","price":140}]}]},{"key":"betrivers","title":"BetRivers","last_update":"2022-10-21T23:54:25Z","markets":[{"key":"h2h","last_update":"2022-10-21T23:54:25Z","outcomes":[{"name":"Phil Hawes","price":-177},{"name":"Roman Dolidze","price":140}]}]},{"key":"unibet_us","title":"Unibet","last_update":"2022-10-21T23:53:39Z","markets":[{"key":"h2h","last_update":"2022-10-21T23:53:39Z","outcomes":[{"name":"Phil Hawes","price":-177},{"name":"Roman Dolidze","price":140}]}]},{"key":"fanduel","title":"FanDuel","last_update":"2022-10-21T23:51:11Z","markets":[{"key":"h2h","last_update":"2022-10-21T23:51:11Z","outcomes":[{"name":"Phil Hawes","price":-174},{"name":"Roman Dolidze","price":146}]}]},{"key":"superbook","title":"SuperBook","last_update":"2022-10-21T23:54:23Z","markets":[{"key":"h2h","last_update":"2022-10-21T23:54:23Z","outcomes":[{"name":"Phil Hawes","price":-165},{"name":"Roman Dolidze","price":145}]}]}]},{"id":"4deca4cd45bb8489d499733cbdb940fb","sport_key":"mma_mixed_martial_arts","sport_title":"MMA","commence_time":"2022-11-13T03:00:00Z","home_team":"Israel Adesanya","away_team":"Alex Pereira","bookmakers":[{"key":"fanduel","title":"FanDuel","last_update":"2022-10-21T23:51:11Z","markets":[{"key":"h2h","last_update":"2022-10-21T23:51:11Z","outcomes":[{"name":"Alex Pereira","price":140},{"name":"Israel Adesanya","price":-166}]}]},{"key":"draftkings","title":"DraftKings","last_update":"2022-10-21T23:51:10Z","markets":[{"key":"h2h","last_update":"2022-10-21T23:51:10Z","outcomes":[{"name":"Alex Pereira","price":140},{"name":"Israel Adesanya","price":-165}]}]},{"key":"betonlineag","title":"BetOnline.ag","last_update":"2022-10-21T23:52:00Z","markets":[{"key":"h2h","last_update":"2022-10-21T23:52:00Z","outcomes":[{"name":"Alex Pereira","price":145},{"name":"Israel Adesanya","price":-167}]}]},{"key":"lowvig","title":"LowVig.ag","last_update":"2022-10-21T23:53:47Z","markets":[{"key":"h2h","last_update":"2022-10-21T23:53:47Z","outcomes":[{"name":"Alex Pereira","price":145},{"name":"Israel Adesanya","price":-165}]}]},{"key":"barstool","title":"Barstool Sportsbook","last_update":"2022-10-21T23:54:23Z","markets":[{"key":"h2h","last_update":"2022-10-21T23:54:23Z","outcomes":[{"name":"Alex Pereira","price":138},{"name":"Israel Adesanya","price":-175}]}]},{"key":"sugarhouse","title":"SugarHouse","last_update":"2022-10-21T23:53:38Z","markets":[{"key":"h2h","last_update":"2022-10-21T23:53:38Z","outcomes":[{"name":"Alex Pereira","price":138},{"name":"Israel Adesanya","price":-175}]}]},{"key":"twinspires","title":"TwinSpires","last_update":"2022-10-21T23:54:23Z","markets":[{"key":"h2h","last_update":"2022-10-21T23:54:23Z","outcomes":[{"name":"Alex Pereira","price":138},{"name":"Israel Adesanya","price":-175}]}]},{"key":"betrivers","title":"BetRivers","last_update":"2022-10-21T23:54:25Z","markets":[{"key":"h2h","last_update":"2022-10-21T23:54:25Z","outcomes":[{"name":"Alex Pereira","price":138},{"name":"Israel Adesanya","price":-175}]}]},{"key":"williamhill_us","title":"William Hill (US)","last_update":"2022-10-21T23:52:52Z","markets":[{"key":"h2h","last_update":"2022-10-21T23:52:52Z","outcomes":[{"name":"Alex Pereira","price":145},{"name":"Israel Adesanya","price":-170}]}]},{"key":"betmgm","title":"BetMGM","last_update":"2022-10-21T23:54:22Z","markets":[{"key":"h2h","last_update":"2022-10-21T23:54:22Z","outcomes":[{"name":"Alex Pereira","price":140},{"name":"Israel Adesanya","price":-165}]}]},{"key":"unibet_us","title":"Unibet","last_update":"2022-10-21T23:53:39Z","markets":[{"key":"h2h","last_update":"2022-10-21T23:53:39Z","outcomes":[{"name":"Alex Pereira","price":138},{"name":"Israel Adesanya","price":-175}]}]}]},{"id":"92e1b89f52c8a0eaf9343ab3fc38d248","sport_key":"mma_mixed_martial_arts","sport_title":"MMA","commence_time":"2022-11-13T03:00:00Z","home_team":"Weili Zhang","away_team":"Carla Esparza","bookmakers":[{"key":"barstool","title":"Barstool Sportsbook","last_update":"2022-10-21T23:54:23Z","markets":[{"key":"h2h","last_update":"2022-10-21T23:54:23Z","outcomes":[{"name":"Carla Esparza","price":285},{"name":"Weili Zhang","price":-385}]}]},{"key":"twinspires","title":"TwinSpires","last_update":"2022-10-21T23:54:23Z","markets":[{"key":"h2h","last_update":"2022-10-21T23:54:23Z","outcomes":[{"name":"Carla Esparza","price":285},{"name":"Weili Zhang","price":-385}]}]},{"key":"sugarhouse","title":"SugarHouse","last_update":"2022-10-21T23:53:38Z","markets":[{"key":"h2h","last_update":"2022-10-21T23:53:38Z","outcomes":[{"name":"Carla Esparza","price":285},{"name":"Weili Zhang","price":-385}]}]},{"key":"betrivers","title":"BetRivers","last_update":"2022-10-21T23:54:25Z","markets":[{"key":"h2h","last_update":"2022-10-21T23:54:25Z","outcomes":[{"name":"Carla Esparza","price":285},{"name":"Weili Zhang","price":-385}]}]},{"key":"fanduel","title":"FanDuel","last_update":"2022-10-21T23:51:11Z","markets":[{"key":"h2h","last_update":"2022-10-21T23:51:11Z","outcomes":[{"name":"Carla Esparza","price":265},{"name":"Weili Zhang","price":-330}]}]},{"key":"draftkings","title":"DraftKings","last_update":"2022-10-21T23:51:10Z","markets":[{"key":"h2h","last_update":"2022-10-21T23:51:10Z","outcomes":[{"name":"Carla Esparza","price":280},{"name":"Weili Zhang","price":-340}]}]},{"key":"betonlineag","title":"BetOnline.ag","last_update":"2022-10-21T23:52:00Z","markets":[{"key":"h2h","last_update":"2022-10-21T23:52:00Z","outcomes":[{"name":"Carla Esparza","price":250},{"name":"Weili Zhang","price":-333}]}]},{"key":"lowvig","title":"LowVig.ag","last_update":"2022-10-21T23:53:47Z","markets":[{"key":"h2h","last_update":"2022-10-21T23:53:47Z","outcomes":[{"name":"Carla Esparza","price":250},{"name":"Weili Zhang","price":-325}]}]},{"key":"williamhill_us","title":"William Hill (US)","last_update":"2022-10-21T23:52:52Z","markets":[{"key":"h2h","last_update":"2022-10-21T23:52:52Z","outcomes":[{"name":"Carla Esparza","price":280},{"name":"Weili Zhang","price":-360}]}]},{"key":"betmgm","title":"BetMGM","last_update":"2022-10-21T23:54:22Z","markets":[{"key":"h2h","last_update":"2022-10-21T23:54:22Z","outcomes":[{"name":"Carla Esparza","price":275},{"name":"Weili Zhang","price":-350}]}]},{"key":"unibet_us","title":"Unibet","last_update":"2022-10-21T23:53:39Z","markets":[{"key":"h2h","last_update":"2022-10-21T23:53:39Z","outcomes":[{"name":"Carla Esparza","price":285},{"name":"Weili Zhang","price":-385}]}]}]},{"id":"9dc497b22a2f5e499ead211a444a59d4","sport_key":"mma_mixed_martial_arts","sport_title":"MMA","commence_time":"2022-11-13T03:00:00Z","home_team":"Dustin Poirier","away_team":"Michael Chandler","bookmakers":[{"key":"fanduel","title":"FanDuel","last_update":"2022-10-21T23:51:11Z","markets":[{"key":"h2h","last_update":"2022-10-21T23:51:11Z","outcomes":[{"name":"Dustin Poirier","price":-168},{"name":"Michael Chandler","price":142}]}]},{"key":"draftkings","title":"DraftKings","last_update":"2022-10-21T23:51:10Z","markets":[{"key":"h2h","last_update":"2022-10-21T23:51:10Z","outcomes":[{"name":"Dustin Poirier","price":-165},{"name":"Michael Chandler","price":140}]}]},{"key":"sugarhouse","title":"SugarHouse","last_update":"2022-10-21T23:53:38Z","markets":[{"key":"h2h","last_update":"2022-10-21T23:53:38Z","outcomes":[{"name":"Dustin Poirier","price":-165},{"name":"Michael Chandler","price":132}]}]},{"key":"barstool","title":"Barstool Sportsbook","last_update":"2022-10-21T23:54:23Z","markets":[{"key":"h2h","last_update":"2022-10-21T23:54:23Z","outcomes":[{"name":"Dustin Poirier","price":-165},{"name":"Michael Chandler","price":132}]}]},{"key":"twinspires","title":"TwinSpires","last_update":"2022-10-21T23:54:23Z","markets":[{"key":"h2h","last_update":"2022-10-21T23:54:23Z","outcomes":[{"name":"Dustin Poirier","price":-165},{"name":"Michael Chandler","price":132}]}]},{"key":"betrivers","title":"BetRivers","last_update":"2022-10-21T23:54:25Z","markets":[{"key":"h2h","last_update":"2022-10-21T23:54:25Z","outcomes":[{"name":"Dustin Poirier","price":-165},{"name":"Michael Chandler","price":132}]}]},{"key":"williamhill_us","title":"William Hill (US)","last_update":"2022-10-21T23:52:52Z","markets":[{"key":"h2h","last_update":"2022-10-21T23:52:52Z","outcomes":[{"name":"Dustin Poirier","price":-160},{"name":"Michael Chandler","price":135}]}]},{"key":"betmgm","title":"BetMGM","last_update":"2022-10-21T23:54:22Z","markets":[{"key":"h2h","last_update":"2022-10-21T23:54:22Z","outcomes":[{"name":"Dustin Poirier","price":-175},{"name":"Michael Chandler","price":145}]}]},{"key":"unibet_us","title":"Unibet","last_update":"2022-10-21T23:53:39Z","markets":[{"key":"h2h","last_update":"2022-10-21T23:53:39Z","outcomes":[{"name":"Dustin Poirier","price":-165},{"name":"Michael Chandler","price":132}]}]},{"key":"betonlineag","title":"BetOnline.ag","last_update":"2022-10-21T23:52:00Z","markets":[{"key":"h2h","last_update":"2022-10-21T23:52:00Z","outcomes":[{"name":"Dustin Poirier","price":-175},{"name":"Michael Chandler","price":150}]}]},{"key":"lowvig","title":"LowVig.ag","last_update":"2022-10-21T23:53:47Z","markets":[{"key":"h2h","last_update":"2022-10-21T23:53:47Z","outcomes":[{"name":"Dustin Poirier","price":-175},{"name":"Michael Chandler","price":150}]}]}]},{"id":"ef00151093557593770fb4a5b861a3f8","sport_key":"mma_mixed_martial_arts","sport_title":"MMA","commence_time":"2022-12-04T05:00:00Z","home_team":"Kevin Holland","away_team":"Stephen Thompson","bookmakers":[{"key":"betonlineag","title":"BetOnline.ag","last_update":"2022-10-21T23:52:00Z","markets":[{"key":"h2h","last_update":"2022-10-21T23:52:00Z","outcomes":[{"name":"Kevin Holland","price":104},{"name":"Stephen Thompson","price":-125}]}]},{"key":"fanduel","title":"FanDuel","last_update":"2022-10-21T23:51:11Z","markets":[{"key":"h2h","last_update":"2022-10-21T23:51:11Z","outcomes":[{"name":"Kevin Holland","price":100},{"name":"Stephen Thompson","price":-118}]}]},{"key":"lowvig","title":"LowVig.ag","last_update":"2022-10-21T23:53:47Z","markets":[{"key":"h2h","last_update":"2022-10-21T23:53:47Z","outcomes":[{"name":"Kevin Holland","price":105},{"name":"Stephen Thompson","price":-125}]}]},{"key":"draftkings","title":"DraftKings","last_update":"2022-10-21T23:51:10Z","markets":[{"key":"h2h","last_update":"2022-10-21T23:51:10Z","outcomes":[{"name":"Kevin Holland","price":-110},{"name":"Stephen Thompson","price":-110}]}]}]},{"id":"88ebd0847ca607e1345a7945d731954d","sport_key":"mma_mixed_martial_arts","sport_title":"MMA","commence_time":"2022-12-11T00:00:00Z","home_team":"Jamie Pickett","away_team":"Bo Nickal","bookmakers":[{"key":"fanduel","title":"FanDuel","last_update":"2022-10-21T23:51:11Z","markets":[{"key":"h2h","last_update":"2022-10-21T23:51:11Z","outcomes":[{"name":"Bo Nickal","price":-2500},{"name":"Jamie Pickett","price":1200}]}]}]},{"id":"5f9be2a24d49ae731bb21f1004662418","sport_key":"mma_mixed_martial_arts","sport_title":"MMA","commence_time":"2022-12-11T03:00:00Z","home_team":"Dricus Du Plessis","away_team":"Darren Till","bookmakers":[{"key":"fanduel","title":"FanDuel","last_update":"2022-10-21T23:51:11Z","markets":[{"key":"h2h","last_update":"2022-10-21T23:51:11Z","outcomes":[{"name":"Darren Till","price":102},{"name":"Dricus Du Plessis","price":-120}]}]},{"key":"betonlineag","title":"BetOnline.ag","last_update":"2022-10-21T23:52:00Z","markets":[{"key":"h2h","last_update":"2022-10-21T23:52:00Z","outcomes":[{"name":"Darren Till","price":115},{"name":"Dricus Du Plessis","price":-135}]}]},{"key":"lowvig","title":"LowVig.ag","last_update":"2022-10-21T23:53:47Z","markets":[{"key":"h2h","last_update":"2022-10-21T23:53:47Z","outcomes":[{"name":"Darren Till","price":115},{"name":"Dricus Du Plessis","price":-135}]}]},{"key":"draftkings","title":"DraftKings","last_update":"2022-10-21T23:51:10Z","markets":[{"key":"h2h","last_update":"2022-10-21T23:51:10Z","outcomes":[{"name":"Darren Till","price":110},{"name":"Dricus Du Plessis","price":-130}]}]}]},{"id":"34abfd3bed4e359ada79810ccc3412f1","sport_key":"mma_mixed_martial_arts","sport_title":"MMA","commence_time":"2022-12-11T03:00:00Z","home_team":"Magomed Ankalaev","away_team":"Jan Blachowicz","bookmakers":[{"key":"fanduel","title":"FanDuel","last_update":"2022-10-21T23:51:11Z","markets":[{"key":"h2h","last_update":"2022-10-21T23:51:11Z","outcomes":[{"name":"Jan Blachowicz","price":188},{"name":"Magomed Ankalaev","price":-225}]}]},{"key":"betonlineag","title":"BetOnline.ag","last_update":"2022-10-21T23:52:00Z","markets":[{"key":"h2h","last_update":"2022-10-21T23:52:00Z","outcomes":[{"name":"Jan Blachowicz","price":210},{"name":"Magomed Ankalaev","price":-250}]}]},{"key":"lowvig","title":"LowVig.ag","last_update":"2022-10-21T23:53:47Z","markets":[{"key":"h2h","last_update":"2022-10-21T23:53:47Z","outcomes":[{"name":"Jan Blachowicz","price":210},{"name":"Magomed Ankalaev","price":-250}]}]},{"key":"draftkings","title":"DraftKings","last_update":"2022-10-21T23:51:10Z","markets":[{"key":"h2h","last_update":"2022-10-21T23:51:10Z","outcomes":[{"name":"Jan Blachowicz","price":180},{"name":"Magomed Ankalaev","price":-210}]}]}]},{"id":"383f92d674a9fe620fa4d67fb95795c5","sport_key":"mma_mixed_martial_arts","sport_title":"MMA","commence_time":"2022-12-11T05:00:00Z","home_team":"Glover Teixeira","away_team":"Jiri Prochazka","bookmakers":[{"key":"fanduel","title":"FanDuel","last_update":"2022-10-21T23:51:11Z","markets":[{"key":"h2h","last_update":"2022-10-21T23:51:11Z","outcomes":[{"name":"Glover Teixeira","price":164},{"name":"Jiri Prochazka","price":-196}]}]},{"key":"betonlineag","title":"BetOnline.ag","last_update":"2022-10-21T23:52:00Z","markets":[{"key":"h2h","last_update":"2022-10-21T23:52:00Z","outcomes":[{"name":"Glover Teixeira","price":163},{"name":"Jiri Prochazka","price":-189}]}]},{"key":"lowvig","title":"LowVig.ag","last_update":"2022-10-21T23:53:47Z","markets":[{"key":"h2h","last_update":"2022-10-21T23:53:47Z","outcomes":[{"name":"Glover Teixeira","price":163},{"name":"Jiri Prochazka","price":-188}]}]},{"key":"draftkings","title":"DraftKings","last_update":"2022-10-21T23:51:10Z","markets":[{"key":"h2h","last_update":"2022-10-21T23:51:10Z","outcomes":[{"name":"Glover Teixeira","price":165},{"name":"Jiri Prochazka","price":-195}]}]}]},{"id":"e8ef65710575e027bbf6063699da4331","sport_key":"mma_mixed_martial_arts","sport_title":"MMA","commence_time":"2023-02-12T05:00:00Z","home_team":"Paulo Henrique Costa","away_team":"Robert Whittaker","bookmakers":[{"key":"fanduel","title":"FanDuel","last_update":"2022-10-21T23:51:11Z","markets":[{"key":"h2h","last_update":"2022-10-21T23:51:11Z","outcomes":[{"name":"Paulo Henrique Costa","price":205},{"name":"Robert Whittaker","price":-250}]}]},{"key":"betonlineag","title":"BetOnline.ag","last_update":"2022-10-21T23:52:00Z","markets":[{"key":"h2h","last_update":"2022-10-21T23:52:00Z","outcomes":[{"name":"Paulo Henrique Costa","price":224},{"name":"Robert Whittaker","price":-270}]}]},{"key":"lowvig","title":"LowVig.ag","last_update":"2022-10-21T23:53:47Z","markets":[{"key":"h2h","last_update":"2022-10-21T23:53:47Z","outcomes":[{"name":"Paulo Henrique Costa","price":224},{"name":"Robert Whittaker","price":-264}]}]},{"key":"draftkings","title":"DraftKings","last_update":"2022-10-21T23:51:10Z","markets":[{"key":"h2h","last_update":"2022-10-21T23:51:10Z","outcomes":[{"name":"Paulo Henrique Costa","price":210},{"name":"Robert Whittaker","price":-250}]}]}]}]}
